Workbook

Sheet Dashboard
A1: Arborescence SEO - Boutique Coloriages Kawaii
A2: Structure de site avec collections basees sur des mots-cles Ahrefs. Chaque collection = un mot-cle cible.
A4: Collections actives | B4: Volume SEO total | C4: SKU cible total | E4: KD moyen pondere | F4: CPC moyen pondere | G4: Prix moyen cible
A5: =COUNTIF(Collections!$D$4:$D$18,"Oui") | B5: =SUM(Collections!$F$4:$F$18) | C5: =SUM(Collections!$K$4:$K$18) | E5: =ROUND(SUMPRODUCT(Collections!$F$4:$F$18,Collections!$G$4:$G$18)/SUM(Collections!$F$4:$F$18),1) | F5: =ROUND(SUMPRODUCT(Collections!$F$4:$F$18,Collections!$H$4:$H$18)/SUMIF(Collections!$H$4:$H$18,">0",Collections!$F$4:$F$18),2) | G5: =ROUND(AVERAGE(Collections!$L$4:$L$18),1)
A8: Roadmap recommandee
A9: 1 | B9: Lancer les collections P1 | C9: Coloriage kawaii, adulte, magique, mystere, cosy et feutre acrylique. | D9: Objectif : capter les plus gros volumes avec des pages de collection solides et des bundles physiques.
A10: 2 | B10: Construire 300+ SKU | C10: Repartir les SKU selon SKU_Plan, en commencant par les packs et kits a forte marge. | D10: Eviter les fichiers gratuits : vendre des objets physiques, lots et personnalisations.
A11: 3 | B11: Maillage interne | C11: Chaque page P2 remonte vers coloriage kawaii et vers l'accessoire le plus logique. | D11: Ex : coloriage manga -> feutre a alcool; coloriage cosy -> marque page personnalise.
A12: 4 | B12: Contenu SEO | C12: Ajouter guides courts sur les pages collection et 8-12 articles blog top-funnel. | D12: Blog uniquement pour alimenter les collections, pas comme destination principale.
A13: 5 | B13: Sourcing | C13: Exclure les licences et personnages proteges. | D13: Utiliser des designs originaux kawaii, chibi, animaux, cocooning, football generique.
A16: Top collections a creer en premier
A17: Priorite | B17: Collection = mot-cle | C17: Volume | D17: SKU cible | E17: Pourquoi
A18: P1 | B18: coloriage kawaii | C18: 38000 | D18: 45 | E18: Page pilier et mot-cle exact-match de la marque.
A19: P1 | B19: feutre acrylique | C19: 33000 | D19: 40 | E19: Accessoire a panier moyen et marge plus forte.
A20: P1 | B20: coloriage adulte | C20: 15000 | D20: 35 | E20: Segment plus premium, bon pour bundles.
A21: P1 | B21: coloriage magique | C21: 13000 | D21: 30 | E21: Giftable enfant, bonne intention produit.
A22: P1 | B22: coloriage mystere | C22: 12000 | D22: 30 | E22: Angle ludique, retention et cross-sell.
A25: Veille concurrentielle - pure players spécialisés
A26: Concurrents qualifiés | B26: Sites français inclus | C26: Menaces hautes | D26: Faux positifs exclus
A27: =COUNTA('Concurrents'!$A$4:$A$17) | B27: =COUNTIF('Concurrents'!$C$4:$C$17,"France / français")+COUNTIF('Concurrents'!$C$4:$C$17,"France / français-anglais") | C27: =COUNTIF('Concurrents'!$M$4:$M$17,"Haute") | D27: =COUNTA('Concurrents'!$A$22:$A$32)
A29: Espace FR encore peu occupé : AICrayons et MyCuttieBox sont les plus proches localement; Belly Bean et Bobbie Goods sont les menaces internationales, Cozykleuren le meilleur modèle de catalogue.

Sheet Arborescence
A1: Arborescence de site - Coloriages Kawaii
A3: Niveau | B3: Type page | C3: Parent | D3: Collection = mot-cle | E3: URL | F3: H1 | G3: Volume FR | H3: KD | I3: CPC | J3: Intention | K3: Priorite | L3: SKU cible | M3: Role SEO | N3: Meta title | O3: Meta description | P3: Maillage interne | Q3: Notes
A4: 0 | B4: Accueil / hub marque | C4: - | D4: coloriage kawaii | E4: / | F4: Coloriage Kawaii | G4: 38000 | H4: 1 | I4: 0.06 | J4: Marque + commerciale | K4: P1 | L4: 0 | M4: Page d'entree marque, rassurance, best-sellers et collections P1. | N4: Coloriage Kawaii | Kits, carnets et feutres mignons | O4: Boutique de coloriages kawaii, carnets creatifs, feutres et kits cadeaux pour enfants et adultes. | P4: Liens directs vers toutes les collections P1 et accessoires. | Q4: Ne pas surcharger en texte : montrer les produits et bundles.
A5: 1 | B5: Hub menu non-collection | C5: / | E5: /univers/coloriage-kawaii | F5: Coloriages kawaii | J5: Navigation | M5: Regroupe les collections sans cannibaliser les mots-cles exacts. | N5: Coloriages kawaii | O5: Selection coloriages pour orienter le visiteur vers les collections. | P5: Liens vers collections du meme pilier. | Q5: Menu principal
A6: 1 | B6: Hub menu non-collection | C6: / | E6: /univers/feutre-acrylique | F6: Feutres et accessoires | J6: Navigation | M6: Regroupe les collections sans cannibaliser les mots-cles exacts. | N6: Feutres et accessoires | O6: Selection accessoires pour orienter le visiteur vers les collections. | P6: Liens vers collections du meme pilier. | Q6: Menu principal
A7: 1 | B7: Hub menu non-collection | C7: / | E7: /univers/diamond-painting-personnalise | F7: Cadeaux creatifs | J7: Navigation | M7: Regroupe les collections sans cannibaliser les mots-cles exacts. | N7: Cadeaux creatifs | O7: Selection cadeaux creatifs pour orienter le visiteur vers les collections. | P7: Liens vers collections du meme pilier. | Q7: Menu principal
A8: 2 | B8: Collection | C8: /univers/coloriages | D8: coloriage kawaii | E8: /collections/coloriage-kawaii | F8: Coloriage Kawaii | G8: 38000 | H8: 1 | I8: 0.06 | J8: Transactionnelle | K8: P1 | L8: 45 | M8: Collection pilier SEO et commerciale | N8: coloriage kawaii | Kits et carnets kawaii | O8: Découvrez notre collection coloriage kawaii : carnets, kits et accessoires créatifs pour une boutique coloriage kawaii. | P8: Depuis accueil + menu + collections P2 liees | Q8: Livres, carnets, packs imprimés, bundles découverte. Page mère à mailler vers tous les thèmes kawaii.
A9: 2 | B9: Collection | C9: /univers/coloriages | D9: coloriage adulte | E9: /collections/coloriage-adulte | F9: Coloriage Adulte | G9: 15000 | H9: 0 | I9: 0.1 | J9: Commerciale | K9: P1 | L9: 35 | M9: Segment panier plus élevé | N9: coloriage adulte | Kits et carnets kawaii | O9: Découvrez notre collection coloriage adulte : carnets, kits et accessoires créatifs pour une boutique coloriage kawaii. | P9: Depuis accueil + menu + collections P2 liees | Q9: Cahiers anti-stress, mandalas kawaii, carnets premium papier épais, packs feutres + livre.
A10: 2 | B10: Collection | C10: /univers/coloriages | D10: coloriage magique | E10: /collections/coloriage-magique | F10: Coloriage Magique | G10: 13000 | H10: 3 | I10: 0.08 | J10: Commerciale | K10: P1 | L10: 30 | M10: Collection enfant/giftable | N10: coloriage magique | Kits et carnets kawaii | O10: Découvrez notre collection coloriage magique : carnets, kits et accessoires créatifs pour une boutique coloriage kawaii. | P10: Depuis accueil + menu + collections P2 liees | Q10: Livres à révélation, feutres magiques, cahiers effaçables, packs cadeaux anniversaire.
A11: 2 | B11: Collection | C11: /univers/coloriages | D11: coloriage mystere | E11: /collections/coloriage-mystere | F11: Coloriage Mystere | G11: 12000 | H11: 0 | I11: 0.09 | J11: Transactionnelle | K11: P1 | L11: 30 | M11: Angle découverte et retention | N11: coloriage mystere | Kits et carnets kawaii | O11: Découvrez notre collection coloriage mystere : carnets, kits et accessoires créatifs pour une boutique coloriage kawaii. | P11: Depuis accueil + menu + collections P2 liees | Q11: Coloriages mystères par numéros, pixels kawaii, animaux cachés, cartes surprises.
A12: 2 | B12: Collection | C12: /univers/coloriages | D12: coloriage cosy | E12: /collections/coloriage-cosy | F12: Coloriage Cosy | G12: 9200 | H12: 0 | I12: 0.11 | J12: Commerciale | K12: P1 | L12: 30 | M12: Positionnement marque cosy | N12: coloriage cosy | Kits et carnets kawaii | O12: Découvrez notre collection coloriage cosy : carnets, kits et accessoires créatifs pour une boutique coloriage kawaii. | P12: Depuis accueil + menu + collections P2 liees | Q12: Univers cocooning : chats, thé, maison, automne, journaling, packs relaxation.
A13: 2 | B13: Collection | C13: /univers/coloriages | D13: coloriage manga | E13: /collections/coloriage-manga | F13: Coloriage Manga | G13: 7000 | H13: 0 | I13: 0.07 | J13: Commerciale | K13: P2 | L13: 25 | M13: Trafic passion mais IP-safe | N13: coloriage manga | Kits et carnets kawaii | O13: Découvrez notre collection coloriage manga : carnets, kits et accessoires créatifs pour une boutique coloriage kawaii. | P13: Depuis page pilier + recommandations produits | Q13: Personnages originaux manga/chibi, expressions, tenues, cahiers apprentissage dessin.
A14: 2 | B14: Collection | C14: /univers/coloriages | D14: coloriage foot | E14: /collections/coloriage-foot | F14: Coloriage Foot | G14: 6600 | H14: 0 | I14: 0.06 | J14: Commerciale | K14: P2 | L14: 25 | M14: Collection cadeau enfant | N14: coloriage foot | Kits et carnets kawaii | O14: Découvrez notre collection coloriage foot : carnets, kits et accessoires créatifs pour une boutique coloriage kawaii. | P14: Depuis page pilier + recommandations produits | Q14: Coloriages football génériques, maillots non licenciés, trophées, ballons, activités anniversaire.
A15: 2 | B15: Collection | C15: /univers/coloriages | D15: coloriage fille | E15: /collections/coloriage-fille | F15: Coloriage Fille | G15: 6600 | H15: 0 | J15: Commerciale | K15: P2 | L15: 25 | M15: Requête large enfant | N15: coloriage fille | Kits et carnets kawaii | O15: Découvrez notre collection coloriage fille : carnets, kits et accessoires créatifs pour une boutique coloriage kawaii. | P15: Depuis page pilier + recommandations produits | Q15: Licornes, animaux mignons, sirènes, mode, stickers. Attention à garder un wording inclusif en site.
A16: 2 | B16: Collection | C16: /univers/coloriages | D16: coloriage kawaii fille | E16: /collections/coloriage-kawaii-fille | F16: Coloriage Kawaii Fille | G16: 4800 | H16: 1 | J16: Transactionnelle | K16: P2 | L16: 25 | M16: Longue traîne transactionnelle | N16: coloriage kawaii fille | Kits et carnets kawaii | O16: Découvrez notre collection coloriage kawaii fille : carnets, kits et accessoires créatifs pour une boutique coloriage kawaii. | P16: Depuis page pilier + recommandations produits | Q16: Déclinaison plus ciblée de la page pilier, à mailler depuis coloriage kawaii et coloriage fille.
A17: 2 | B17: Collection | C17: /univers/themes-kawaii | D17: chat kawaii | E17: /collections/chat-kawaii | F17: Chat Kawaii | G17: 4200 | H17: 0 | I17: 0.06 | J17: Commerciale | K17: P2 | L17: 20 | M17: Thème très brandable | N17: chat kawaii | Kits et carnets kawaii | O17: Découvrez notre collection chat kawaii : carnets, kits et accessoires créatifs pour une boutique coloriage kawaii. | P17: Depuis page pilier + recommandations produits | Q17: Collection de livres, stickers, marque-pages et mini kits autour du chat kawaii.
A18: 2 | B18: Collection | C18: /univers/accessoires | D18: feutre acrylique | E18: /collections/feutre-acrylique | F18: Feutre Acrylique | G18: 33000 | H18: 0 | I18: 0.16 | J18: Transactionnelle | K18: P1 | L18: 40 | M18: Monétisation accessoire forte | N18: feutre acrylique | Kits et carnets kawaii | O18: Découvrez notre collection feutre acrylique : carnets, kits et accessoires créatifs pour une boutique coloriage kawaii. | P18: Depuis accueil + menu + collections P2 liees | Q18: Sets de feutres, pointes fines, packs couleurs pastel, bundle avec cahiers papier épais.
A19: 2 | B19: Collection | C19: /univers/accessoires | D19: feutre a alcool | E19: /collections/feutre-a-alcool | F19: Feutre A Alcool | G19: 5400 | H19: 0 | I19: 0.21 | J19: Transactionnelle | K19: P2 | L19: 30 | M19: Panier moyen et upsell | N19: feutre a alcool | Kits et carnets kawaii | O19: Découvrez notre collection feutre a alcool : carnets, kits et accessoires créatifs pour une boutique coloriage kawaii. | P19: Depuis page pilier + recommandations produits | Q19: Sets alcohol markers, nuanciers, pochettes rangement, packs débutant et premium.
A20: 2 | B20: Collection | C20: /univers/accessoires | D20: trousse kawaii | E20: /collections/trousse-kawaii | F20: Trousse Kawaii | G20: 3800 | H20: 0 | I20: 0.14 | J20: Transactionnelle | K20: P2 | L20: 20 | M20: Produit léger et cadeau | N20: trousse kawaii | Kits et carnets kawaii | O20: Découvrez notre collection trousse kawaii : carnets, kits et accessoires créatifs pour une boutique coloriage kawaii. | P20: Depuis page pilier + recommandations produits | Q20: Trousses mignonnes, pochettes feutres, rangement coloriage, lots rentrée.
A21: 2 | B21: Collection | C21: /univers/cadeaux-creatifs | D21: marque page personnalisé | E21: /collections/marque-page-personnalise | F21: Marque Page Personnalisé | G21: 3700 | H21: 1 | I21: 0.42 | J21: Transactionnelle | K21: P2 | L21: 20 | M21: AOV par personnalisation | N21: marque page personnalisé | Kits et carnets kawaii | O21: Découvrez notre collection marque page personnalisé : carnets, kits et accessoires créatifs pour une boutique coloriage kawaii. | P21: Depuis page pilier + recommandations produits | Q21: Marque-pages prénom, chats, fleurs, citations, lots de 3 et bundle cahier.
A22: 2 | B22: Collection | C22: /univers/cadeaux-creatifs | D22: diamond painting personnalisé | E22: /collections/diamond-painting-personnalise | F22: Diamond Painting Personnalisé | G22: 6000 | H22: 2 | I22: 0.71 | J22: Transactionnelle | K22: P2 | L22: 30 | M22: Produit cadeau à marge | N22: diamond painting personnalisé | Kits et carnets kawaii | O22: Découvrez notre collection diamond painting personnalisé : carnets, kits et accessoires créatifs pour une boutique coloriage kawaii. | P22: Depuis page pilier + recommandations produits | Q22: Kits personnalisés, formats petits faciles à expédier, modèles animaux kawaii.
A23: 1 | B23: Blog SEO | C23: / | E23: /blogs/guides | F23: Guides coloriage kawaii | J23: Informationnelle | K23: P3 | M23: Alimenter les collections, pas remplacer les pages transactionnelles. | N23: Guides coloriage kawaii | O23: Idees, conseils feutres et inspirations pour mieux colorier. | P23: Chaque article doit pointer vers une collection. | Q23: Exemples : comment choisir ses feutres, coloriage kawaii adulte, idees cadeaux.
A24: 1 | B24: Pages confiance | C24: / | E24: /pages/livraison-retours | F24: Livraison et retours | J24: Rassurance | K24: P2 | M24: Limiter la friction avant achat. | N24: Livraison et retours | O24: Delais, suivi et retours pour les kits coloriage kawaii. | P24: Footer + checkout. | Q24: Essentiel pour dropshipping : clarifier delais et suivi.

Sheet Collections
A1: Collections SEO - 1 collection = 1 mot-cle
A3: Ordre | B3: Pilier | C3: Collection = mot-cle | D3: Active | E3: URL | F3: Volume FR | G3: KD | H3: CPC | I3: Intention | J3: Priorite | K3: SKU cible | L3: Prix moyen cible | M3: Score SEO | N3: Role commercial | O3: Brief collection | P3: Source CSV keyword
A4: 1 | B4: Coloriages | C4: coloriage kawaii | D4: Oui | E4: /collections/coloriage-kawaii | F4: 38000 | G4: 1 | H4: 0.06 | I4: Transactionnelle | J4: P1 | K4: 45 | L4: 24.9 | M4: =ROUND((F4/(G4+1))*IF(J4="P1",1.2,IF(J4="P2",1,0.8)),0) | N4: Collection pilier SEO et commerciale | O4: Livres, carnets, packs imprimés, bundles découverte. Page mère à mailler vers tous les thèmes kawaii. | P4: coloriage kawaii
A5: 2 | B5: Coloriages | C5: coloriage adulte | D5: Oui | E5: /collections/coloriage-adulte | F5: 15000 | G5: 0 | H5: 0.1 | I5: Commerciale | J5: P1 | K5: 35 | L5: 29.9 | M5: =ROUND((F5/(G5+1))*IF(J5="P1",1.2,IF(J5="P2",1,0.8)),0) | N5: Segment panier plus élevé | O5: Cahiers anti-stress, mandalas kawaii, carnets premium papier épais, packs feutres + livre. | P5: coloriage adulte
A6: 3 | B6: Coloriages | C6: coloriage magique | D6: Oui | E6: /collections/coloriage-magique | F6: 13000 | G6: 3 | H6: 0.08 | I6: Commerciale | J6: P1 | K6: 30 | L6: 22.9 | M6: =ROUND((F6/(G6+1))*IF(J6="P1",1.2,IF(J6="P2",1,0.8)),0) | N6: Collection enfant/giftable | O6: Livres à révélation, feutres magiques, cahiers effaçables, packs cadeaux anniversaire. | P6: coloriage magique
A7: 4 | B7: Coloriages | C7: coloriage mystere | D7: Oui | E7: /collections/coloriage-mystere | F7: 12000 | G7: 0 | H7: 0.09 | I7: Transactionnelle | J7: P1 | K7: 30 | L7: 24.9 | M7: =ROUND((F7/(G7+1))*IF(J7="P1",1.2,IF(J7="P2",1,0.8)),0) | N7: Angle découverte et retention | O7: Coloriages mystères par numéros, pixels kawaii, animaux cachés, cartes surprises. | P7: coloriage mystere
A8: 5 | B8: Coloriages | C8: coloriage cosy | D8: Oui | E8: /collections/coloriage-cosy | F8: 9200 | G8: 0 | H8: 0.11 | I8: Commerciale | J8: P1 | K8: 30 | L8: 27.9 | M8: =ROUND((F8/(G8+1))*IF(J8="P1",1.2,IF(J8="P2",1,0.8)),0) | N8: Positionnement marque cosy | O8: Univers cocooning : chats, thé, maison, automne, journaling, packs relaxation. | P8: coloriage cosy
A9: 6 | B9: Coloriages | C9: coloriage manga | D9: Oui | E9: /collections/coloriage-manga | F9: 7000 | G9: 0 | H9: 0.07 | I9: Commerciale | J9: P2 | K9: 25 | L9: 24.9 | M9: =ROUND((F9/(G9+1))*IF(J9="P1",1.2,IF(J9="P2",1,0.8)),0) | N9: Trafic passion mais IP-safe | O9: Personnages originaux manga/chibi, expressions, tenues, cahiers apprentissage dessin. | P9: coloriage manga
A10: 7 | B10: Coloriages | C10: coloriage foot | D10: Oui | E10: /collections/coloriage-foot | F10: 6600 | G10: 0 | H10: 0.06 | I10: Commerciale | J10: P2 | K10: 25 | L10: 19.9 | M10: =ROUND((F10/(G10+1))*IF(J10="P1",1.2,IF(J10="P2",1,0.8)),0) | N10: Collection cadeau enfant | O10: Coloriages football génériques, maillots non licenciés, trophées, ballons, activités anniversaire. | P10: coloriage foot
A11: 8 | B11: Coloriages | C11: coloriage fille | D11: Oui | E11: /collections/coloriage-fille | F11: 6600 | G11: 0 | I11: Commerciale | J11: P2 | K11: 25 | L11: 19.9 | M11: =ROUND((F11/(G11+1))*IF(J11="P1",1.2,IF(J11="P2",1,0.8)),0) | N11: Requête large enfant | O11: Licornes, animaux mignons, sirènes, mode, stickers. Attention à garder un wording inclusif en site. | P11: coloriage fille
A12: 9 | B12: Coloriages | C12: coloriage kawaii fille | D12: Oui | E12: /collections/coloriage-kawaii-fille | F12: 4800 | G12: 1 | I12: Transactionnelle | J12: P2 | K12: 25 | L12: 19.9 | M12: =ROUND((F12/(G12+1))*IF(J12="P1",1.2,IF(J12="P2",1,0.8)),0) | N12: Longue traîne transactionnelle | O12: Déclinaison plus ciblée de la page pilier, à mailler depuis coloriage kawaii et coloriage fille. | P12: coloriage kawaii fille
A13: 10 | B13: Thèmes kawaii | C13: chat kawaii | D13: Oui | E13: /collections/chat-kawaii | F13: 4200 | G13: 0 | H13: 0.06 | I13: Commerciale | J13: P2 | K13: 20 | L13: 22.9 | M13: =ROUND((F13/(G13+1))*IF(J13="P1",1.2,IF(J13="P2",1,0.8)),0) | N13: Thème très brandable | O13: Collection de livres, stickers, marque-pages et mini kits autour du chat kawaii. | P13: chat kawaii
A14: 11 | B14: Accessoires | C14: feutre acrylique | D14: Oui | E14: /collections/feutre-acrylique | F14: 33000 | G14: 0 | H14: 0.16 | I14: Transactionnelle | J14: P1 | K14: 40 | L14: 29.9 | M14: =ROUND((F14/(G14+1))*IF(J14="P1",1.2,IF(J14="P2",1,0.8)),0) | N14: Monétisation accessoire forte | O14: Sets de feutres, pointes fines, packs couleurs pastel, bundle avec cahiers papier épais. | P14: feutre acrylique
A15: 12 | B15: Accessoires | C15: feutre a alcool | D15: Oui | E15: /collections/feutre-a-alcool | F15: 5400 | G15: 0 | H15: 0.21 | I15: Transactionnelle | J15: P2 | K15: 30 | L15: 34.9 | M15: =ROUND((F15/(G15+1))*IF(J15="P1",1.2,IF(J15="P2",1,0.8)),0) | N15: Panier moyen et upsell | O15: Sets alcohol markers, nuanciers, pochettes rangement, packs débutant et premium. | P15: feutre a alcool
A16: 13 | B16: Accessoires | C16: trousse kawaii | D16: Oui | E16: /collections/trousse-kawaii | F16: 3800 | G16: 0 | H16: 0.14 | I16: Transactionnelle | J16: P2 | K16: 20 | L16: 19.9 | M16: =ROUND((F16/(G16+1))*IF(J16="P1",1.2,IF(J16="P2",1,0.8)),0) | N16: Produit léger et cadeau | O16: Trousses mignonnes, pochettes feutres, rangement coloriage, lots rentrée. | P16: trousse kawaii
A17: 14 | B17: Cadeaux creatifs | C17: marque page personnalisé | D17: Oui | E17: /collections/marque-page-personnalise | F17: 3700 | G17: 1 | H17: 0.42 | I17: Transactionnelle | J17: P2 | K17: 20 | L17: 14.9 | M17: =ROUND((F17/(G17+1))*IF(J17="P1",1.2,IF(J17="P2",1,0.8)),0) | N17: AOV par personnalisation | O17: Marque-pages prénom, chats, fleurs, citations, lots de 3 et bundle cahier. | P17: marque page personnalisé
A18: 15 | B18: Cadeaux creatifs | C18: diamond painting personnalisé | D18: Oui | E18: /collections/diamond-painting-personnalise | F18: 6000 | G18: 2 | H18: 0.71 | I18: Transactionnelle | J18: P2 | K18: 30 | L18: 34.9 | M18: =ROUND((F18/(G18+1))*IF(J18="P1",1.2,IF(J18="P2",1,0.8)),0) | N18: Produit cadeau à marge | O18: Kits personnalisés, formats petits faciles à expédier, modèles animaux kawaii. | P18: diamond painting personnalisé

Sheet SKU_Plan
A1: Plan SKU - 300+ produits sans sortir du theme
A3: Collection = mot-cle | B3: Pilier | C3: SKU cible | D3: Prix moyen cible | E3: Repartition SKU | F3: Exemples produits | G3: Bundle prioritaire | H3: Recherche sourcing AliExpress | I3: Priorite | J3: Risque a eviter
A4: coloriage kawaii | B4: Coloriages | C4: 45 | D4: 24.9 | E4: 15 livres thématiques, 10 carnets, 10 packs pages, 5 bundles feutres, 5 éditions cadeau | F4: Livres, carnets, packs imprimés, bundles découverte. Page mère à mailler vers tous les thèmes kawaii. | G4: Bundle coloriage kawaii + feutres + marque-page | H4: kawaii coloring book, cute coloring pages book, kids coloring book bundle | I4: P1 | J4: Verifier qualite papier, delais, packaging et photos fournisseurs.
A5: coloriage adulte | B5: Coloriages | C5: 35 | D5: 29.9 | E5: 12 livres premium, 8 mandalas kawaii, 6 kits relaxation, 5 carnets papier épais, 4 bundles | F5: Cahiers anti-stress, mandalas kawaii, carnets premium papier épais, packs feutres + livre. | G5: Bundle coloriage adulte + feutres + marque-page | H5: adult coloring book, stress relief coloring book, cute mandala coloring | I5: P1 | J5: Verifier qualite papier, delais, packaging et photos fournisseurs.
A6: coloriage magique | B6: Coloriages | C6: 30 | D6: 22.9 | E6: 10 livres eau, 8 feutres magiques, 6 cahiers réutilisables, 4 sets anniversaire, 2 packs voyage | F6: Livres à révélation, feutres magiques, cahiers effaçables, packs cadeaux anniversaire. | G6: Bundle coloriage magique + feutres + marque-page | H6: magic coloring book, reusable coloring book, water coloring book | I6: P1 | J6: Verifier qualite papier, delais, packaging et photos fournisseurs.
A7: coloriage mystere | B7: Coloriages | C7: 30 | D7: 24.9 | E7: 10 livres par numéros, 8 pixel art, 6 cartes mystère, 4 packs animaux, 2 mini formats | F7: Coloriages mystères par numéros, pixels kawaii, animaux cachés, cartes surprises. | G7: Bundle coloriage mystere + feutres + marque-page | H7: mystery coloring book, color by number cute, pixel coloring book | I7: P1 | J7: Verifier qualite papier, delais, packaging et photos fournisseurs.
A8: coloriage cosy | B8: Coloriages | C8: 30 | D8: 27.9 | E8: 10 livres cocooning, 6 automne, 5 chats, 5 cottagecore, 4 bundles détente | F8: Univers cocooning : chats, thé, maison, automne, journaling, packs relaxation. | G8: Bundle coloriage cosy + feutres + marque-page | H8: cozy coloring book, cottagecore coloring book, cute home coloring | I8: P1 | J8: Verifier qualite papier, delais, packaging et photos fournisseurs.
A9: coloriage manga | B9: Coloriages | C9: 25 | D9: 24.9 | E9: 8 chibi, 6 personnages originaux, 5 expressions, 4 tenues, 2 apprentissage dessin | F9: Personnages originaux manga/chibi, expressions, tenues, cahiers apprentissage dessin. | G9: Bundle coloriage manga + feutres + marque-page | H9: manga coloring book, chibi coloring book, anime style coloring book | I9: P2 | J9: Eviter personnages sous licence et visuels copies.
A10: coloriage foot | B10: Coloriages | C10: 25 | D10: 19.9 | E10: 8 cahiers football, 6 packs anniversaire, 5 ballons/trophées, 4 mini livres, 2 stickers | F10: Coloriages football génériques, maillots non licenciés, trophées, ballons, activités anniversaire. | G10: Bundle coloriage foot + feutres + marque-page | H10: football coloring book, soccer coloring pages book, sports coloring book | I10: P2 | J10: Verifier qualite papier, delais, packaging et photos fournisseurs.
A11: coloriage fille | B11: Coloriages | C11: 25 | D11: 19.9 | E11: 8 licornes, 6 animaux, 5 sirènes, 4 mode, 2 packs stickers | F11: Licornes, animaux mignons, sirènes, mode, stickers. Attention à garder un wording inclusif en site. | G11: Bundle coloriage fille + feutres + marque-page | H11: girls coloring book, unicorn coloring book, cute animals coloring | I11: P2 | J11: Verifier qualite papier, delais, packaging et photos fournisseurs.
A12: coloriage kawaii fille | B12: Coloriages | C12: 25 | D12: 19.9 | E12: 8 livres kawaii, 6 animaux, 5 sirènes/licornes, 4 mini carnets, 2 bundles | F12: Déclinaison plus ciblée de la page pilier, à mailler depuis coloriage kawaii et coloriage fille. | G12: Bundle coloriage kawaii fille + feutres + marque-page | H12: kawaii girl coloring book, cute coloring book girl, kawaii activity book | I12: P2 | J12: Verifier qualite papier, delais, packaging et photos fournisseurs.
A13: chat kawaii | B13: Thèmes kawaii | C13: 20 | D13: 22.9 | E13: 8 livres chats, 4 stickers, 4 marque-pages, 2 cartes, 2 mini carnets | F13: Collection de livres, stickers, marque-pages et mini kits autour du chat kawaii. | G13: Bundle chat kawaii + feutres + marque-page | H13: kawaii cat coloring book, cute cat stationery, cat sticker book | I13: P2 | J13: Eviter personnages sous licence et visuels copies.
A14: feutre acrylique | B14: Accessoires | C14: 40 | D14: 29.9 | E14: 12 sets pastel, 8 pointes fines, 6 double pointe, 6 kits surfaces, 8 bundles | F14: Sets de feutres, pointes fines, packs couleurs pastel, bundle avec cahiers papier épais. | G14: Bundle feutre acrylique + coloriage kawaii | H14: acrylic markers set pastel, acrylic paint pens, dual tip acrylic markers | I14: P1 | J14: Verifier qualite papier, delais, packaging et photos fournisseurs.
A15: feutre a alcool | B15: Accessoires | C15: 30 | D15: 34.9 | E15: 10 sets débutant, 8 sets premium, 5 nuanciers, 4 pochettes, 3 bundles livre | F15: Sets alcohol markers, nuanciers, pochettes rangement, packs débutant et premium. | G15: Bundle feutre a alcool + coloriage kawaii | H15: alcohol markers set, dual tip alcohol marker, marker storage case | I15: P2 | J15: Verifier qualite papier, delais, packaging et photos fournisseurs.
... A18: diamond painting personnalisé | B18: Cadeaux creatifs | C18: 30 | D18: 34.9 | E18: 10 formats portrait, 6 animaux, 5 mini kits, 5 packs cadeau, 4 accessoires | F18: Kits personnalisés, formats petits faciles à expédier, modèles animaux kawaii. | G18: Bundle diamond painting personnalisé + feutres + marque-page | H18: custom diamond painting kit, personalized diamond painting, small diamond art kit | I18: P2 | J18: Verifier qualite papier, delais, packaging et photos fournisseurs.

Sheet Concurrents
A1: Concurrents spécialisés - coloriage kawaii et cosy
A2: Pure players et mini-marques vérifiés le 2026-07-10. Marketplaces, grandes enseignes et sites sans vente directe sont exclus.
A3: Concurrent | B3: URL | C3: Pays / langue | D3: Livraison France | E3: Positionnement | F3: Spécialisation | G3: Prix repère | H3: Maturité visible | I3: Forces | J3: Faiblesses | K3: Opportunité pour la boutique | L3: URL de preuve | M3: Menace FR | N3: Date vérification
A4: AICrayons | B4: https://aicrayons.fr/ | C4: France / français | D4: Oui - acteur local | E4: Carnets physiques et PDF kawaii, chibi, cosy, fantasy et grayscale. | F4: Très proche | G4: 13,90 EUR le carnet spiralé observé | H4: Catalogue étoffé, CGV et retours structurés; peu d'avis visibles. | I4: Livraison locale, physique + numérique, papier 120 g, prix accessible. | J4: Univers graphique dispersé et peu incarné. | K4: Construire une marque kawaii cohérente avec mascottes et preuves de qualité. | L4: https://aicrayons.fr/produit/carnet-a-spirale-les-zanimaux-kawaii/ | M4: Haute | N4: 2026-07-10
A5: MyCuttieBox | B5: https://mycuttiebox.fr/ | C5: France / français | D5: Oui - acteur local | E5: Box cosy avec carnet, marqueur blanc, bougie, stickers et bijou de sac. | F5: Concept extrêmement proche | G5: 24,90-29,90 EUR la box | H5: Première édition en précommande; bonus limité aux premières commandes. | I5: Concept cadeau, panier moyen supérieur, mascottes et illustrations propriétaires. | J5: Faible profondeur de catalogue, logistique de box, offre encore saisonnière. | K5: Déployer des collections permanentes et des kits personnalisables. | L5: https://mycuttiebox.fr/precommande/product-box-cosy-page | M5: Haute | N5: 2026-07-10
A6: Nippon Kawaii | B6: https://www.nipponkawaii.nl/en/ | C6: Pays-Bas / NL-EN-DE | D6: Oui - expédition UE | E6: Boutique kawaii avec livres cosy, peluches, papeterie et accessoires. | F6: Proche - coloriage secondaire | G6: Livraison France affichée à partir de 9,99 EUR | H6: Depuis 2016, 540+ avis et note annoncée de 9,8/10. | I6: Confiance, stock UE, licences officielles, expédition rapide et cross-sell. | J6: Peu de livres cosy, ruptures et aucune localisation française. | K6: Proposer plus de profondeur, du SEO français et des bundles spécialisés. | L6: https://www.nipponkawaii.nl/en/collections/cozy-coloring-books-1 | M6: Moyenne | N6: 2026-07-10
A7: Cozykleuren.nl | B7: https://cozykleuren.nl/ | C7: Pays-Bas / néerlandais | D7: France sélectionnable; tarif à confirmer | E7: Livres cosy, marqueurs alcool, crayons et accessoires de protection. | F7: Coloriage pur | G7: N/D pour la France | H7: Équipe de quatre, entrepôt, société et TVA affichés. | I7: Arborescence aboutie, assortiment livres + consommables, hausse de panier. | J7: Pas de français, livraison France peu claire et ruptures visibles. | K7: Répliquer le modèle catalogue en version française avec stock fiable. | L7: https://cozykleuren.nl/pages/over-ons | M7: Moyenne | N7: 2026-07-10
A8: Bobbie Goods | B8: https://bobbiegoods.com/ | C8: États-Unis / anglais | D8: Oui - international | E8: Livres premium et accessoires autour de personnages propriétaires. | F8: Pur cute/cozy coloring | G8: 22 USD le livre observé | H8: Marque familiale depuis 2021; une référence à 584 avis, 98% positifs. | I8: Univers reconnaissable, rareté, papier épais et communauté forte. | J8: Frais, douane et délais internationaux; peu de pages par livre. | K8: Qualité comparable avec stock UE et prix livré inférieur. | L8: https://bobbiegoods.com/products/this-n-that-coloring-book | M8: Moyenne | N8: 2026-07-10
A9: Belly Bean Co. | B9: https://bellybeanco.com/ | C9: Canada / anglais + éditions françaises | D9: Oui - international | E9: Livres physiques et PDF cute/cozy, éditions françaises et livres techniques. | F9: Pur cute/cozy coloring | G9: 12-29 CAD; éditions françaises autour de 16 CAD | H9: Catalogue profond, collaboration éditoriale et présence sur cinq réseaux. | I9: Éditions françaises, papier premium, thèmes et formats variés. | J9: Expédition canadienne coûteuse et quelques affichages produit confus. | K9: Faire mieux sur le coût rendu, le stock UE et la clarté du catalogue. | L9: https://bellybeanco.com/ | M9: Haute | N9: 2026-07-10
A10: Chloe & Maisy Co. | B10: https://chloeandmaisy.com/ | C10: États-Unis / anglais | D10: Oui - livraison mondiale annoncée | E10: Livres et PDF autour de deux personnages propriétaires, plus protège-pages. | F10: Pur cute/cozy coloring | G10: 22,99 USD le livre; bundle autour de 62,99 USD | H10: Environ 120 avis visibles, galerie clients et vente exclusivement directe. | I10: Personnages propriétaires, papier premium et storytelling fort. | J10: Catalogue étroit, anglais et droits de douane potentiels. | K10: Créer un univers propriétaire francophone avec davantage de collections. | L10: https://chloeandmaisy.com/pages/faq | M10: Moyenne | N10: 2026-07-10
A11: Giggles & Grace Books | B11: https://www.gigglesandgracebooks.com/ | C11: États-Unis / anglais | D11: Oui - livraison mondiale annoncée | E11: 25+ éditions revendiquées, livres physiques, PDF, personnalisation et B2B. | F11: Coloriage pur | G11: 7,99-12,99 USD physique; 1,99-2,99 USD PDF | H11: Catalogue profond, portail wholesale et papier 120 g. | I11: Prix, profondeur, personnalisation et offre professionnelle. | J11: Quelques incohérences visibles dans les chiffres marketing et les avis. | K11: Combiner profondeur catalogue et preuves de confiance plus solides. | L11: https://www.gigglesandgracebooks.com/ | M11: Moyenne | N11: 2026-07-10
A12: Amélie's Workshop | B12: https://ameliesworkshop.fr/en | C12: France / français-anglais | D12: Oui - expédition locale | E12: Livres kawaii/cozy sur le Japon, stickers, marque-pages et carnets. | F12: Proche - papeterie élargie | G12: 9,95-18 EUR les livres observés | H12: Entreprise indépendante depuis 2017, expédition annoncée en 3-4 jours. | I12: Univers d'illustratrice, collections saisonnières et logistique locale. | J12: Le catalogue de papeterie dilue la spécialisation coloriage. | K12: Être plus profond sur le coloriage et structurer les thèmes en collections SEO. | L12: https://ameliesworkshop.fr/en | M12: Moyenne | N12: 2026-07-10
A13: Whimsy Tales | B13: https://whimsytales.com/ | C13: Indonésie/Canada / anglais | D13: Numérique; pas de physique sur le site | E13: Références numériques kawaii/fantasy, blog SEO, échantillons et newsletter. | F13: Proche - numérique | G13: 7-18 CAD sur les références observées | H13: Environ 19 références et narration de marque structurée. | I13: Illustrations originales, contenu organique et acquisition par échantillons. | J13: Aucun produit physique expédié depuis le domaine. | K13: Occuper le physique et les bundles tout en gardant une stratégie de contenu. | L13: https://whimsytales.com/policies/shipping-policy | M13: Faible | N13: 2026-07-10
A14: Bloom & Bolt | B14: https://bloomandboltcoloring.com/ | C14: États-Unis probable / anglais | D14: Oui - international au checkout | E14: Livres spiralés premium, PDF, bundles et pinces de maintien. | F14: Pur cozy coloring | G14: 22,99-24,99 USD physique; 5 USD PDF | H14: Marque émergente, cinq livres physiques, six numériques et peu d'avis. | I14: Papier épais, reliure à plat, accessoires utiles et bundles. | J14: Prix livré élevé pour la France et preuve sociale faible. | K14: Reprendre les bénéfices d'usage avec une livraison européenne. | L14: https://bloomandboltcoloring.com/pages/faq | M14: Faible | N14: 2026-07-10
... A17: Kawaii Sprouts | B17: https://www.kawaiisprouts.com/ | C17: Pays non affiché / anglais | D17: Expédition mondiale annoncée | E17: Personnages originaux, livre principal et petits packs numériques. | F17: Kawaii pur | G17: 2,99-5,99 USD sur les petits packs | H17: Très petite marque, catalogue court et peu de signaux de vente. | I17: Personnages propriétaires et prix d'entrée faible. | J17: Offre physique/PDF parfois ambiguë et expérience encore artisanale. | K17: Plus de transparence, fiches françaises et marque plus professionnelle. | L17: https://www.kawaiisprouts.com/products/kawaii-sprout-50-page-coloring-book | M17: Faible | N17: 2026-07-10
A20: Faux positifs exclus
A21: Site | B21: URL | C21: Motif d'exclusion
A22: Coco Wyo | B22: https://cocowyo.com/pages/faq | C22: Le site officiel renvoie vers Amazon, Etsy ou TikTok Shop; pas de boutique DTC comparable.
A23: Didi Plums | B23: https://www.didiplums.com/paperbacks/cozy-worlds | C23: Les fiches observées renvoient vers Amazon pour l'achat.
A24: Colored Caramel | B24: https://www.coloredcaramel.com/about/ | C24: Catalogue servant de passerelle vers des marketplaces.
A25: Kiki Coloring Studio | B25: https://www.kikicoloringstudio.nl/ | C25: Micro-boutique pertinente mais vente directe limitée aux Pays-Bas.
A26: The Blue Lemon Studio | B26: https://www.thebluelemonstudio.com/ | C26: Achat via Amazon et univers davantage architectural que kawaii.
A27: Aiko Miku | B27: https://aikomiku.de/ | C27: Créatrice kawaii/chibi mais ventes identifiées via Amazon.
A28: OMY | B28: https://omy-maison.com/ | C28: Marque de loisirs créatifs trop généraliste pour le périmètre mini-marque spécialisée.
A29: Vivi Tinta | B29: https://www.vivitinta.com/pages/fqas | C29: Le site officiel indique que les achats passent par Amazon.
A30: Willa Grimshaw | B30: https://willagrimshaw.com/ | C30: Site vitrine conduisant vers Amazon ou Etsy.
A31: Selifu | B31: https://selifu.com/ | C31: Site vitrine conduisant vers Amazon ou Etsy.
A32: Southern Lotus | B32: https://www.southernlotus.com/en/shipping-policy | C32: Boutique directe pertinente mais livraison France non confirmée.

Sheet Sourcing_AliExpress
A1: Sourcing AliExpress - 5 produits à vérifier par collection
A2: 75 emplacements préparés. Les URL et métriques restent vides tant qu'elles ne proviennent pas d'un export AliExpress/DSers ou d'une liste de liens vérifiable.
A3: ID | B3: Collection | C3: Produit | D3: URL AliExpress | E3: Prix produit EUR | F3: Livraison EUR | G3: Coût rendu EUR | H3: Prix cible EUR | I3: Marge x | J3: Note | K3: Commandes | L3: Boutique | M3: Délai France | N3: Choice / UE | O3: Variantes / lot | P3: Angle commercial | Q3: Risques / contrôles | R3: Verdict | S3: Date vérification | T3: Statut / source | U3: Prompts images (carrousel x5) | V3: Dossier images (base PNG) | W3: Titre SEO | X3: Meta title | Y3: Meta description | Z3: Description AIDA (HTML)
A4: coloriage-kawaii-1 | B4: coloriage kawaii | C4: Livre de coloriage magique à l'eau (enfant) | D4: https://fr.aliexpress.com/item/1005006861918127.html | E4: 4.19 | F4: 0 | G4: =IF(OR(E4="",F4=""),"",E4+F4) | H4: =IFERROR(VLOOKUP(B4,'Collections'!$C$4:$L$18,10,FALSE),"") | I4: =IFERROR(H4/G4,"") | J4: 4.9 | K4: 10000 | L4: Choice — vendeur agrégé (non nominatif) | M4: 16-19 juil. (~6-9 j) | N4: Choice | O4: 1pc pen random (livre magique à l'eau) | P4: Coloriage à l'eau réutilisable & sans tache — cadeau enfant / voyage | Q4: JOUET ENFANT : conformité CE/EN71 + GPSR requise ; avertissement suffocation (petites pièces, <3 ans) ; exiger docs conformité fournisseur. Visuels génériques (OK licence). | R4: Retenir | S4: 46213 | T4: AliExpress Choice ; prix Deal du Jour (base 4,21€) ; livraison gratuite dès 10€ d'achat ; note agrégée multi-vendeurs ; JOUET CE/EN71/GPSR a valider avant lancement | U4: PACKSHOT — E-commerce hero packshot of the coloring book «Livre de coloriage magique à l'eau (enfant)», cover facing forward, centered on a clean seamless pastel background, soft studio shadow, ultra-sharp, soft pastel kawaii brand aesthetic, cohesive palette (blush pink, cream, mint, lilac), 1:1 square. LIFESTYLE — Top-down flat-lay of «Livre de coloriage magique à l'eau (enfant)» on a cozy pastel desk with colored pencils, a warm drink and a small plush, soft natural morning light, hygge kawaii mood, soft pastel kawaii brand aesthetic, cohesive palette (blush pink, cream, mint, lilac), 1:1. EN SITUATION — Close-up of a person's hands coloring a kawaii page from «Livre de coloriage magique à l'eau (enfant)», cozy blanket, shallow depth of field, warm soft tones. DÉTAIL — Macro of the open inner pages of «Livre de coloriage magique à l'eau (enfant)» showing cute kawaii line-art illustrations, crisp lines, shallow depth of field. FEATURE — Clean product feature image of «Livre de coloriage magique à l'eau (enfant)» standing upright with minimal text callouts (page count, thick paper, anti-stress), soft pastel kawaii brand aesthetic, cohesive palette (blush pink, cream, mint, lilac), generous negative space for headline. | V4: .../outputs/coloriage-kawaii-arborescence-2026-07-09/images_produits/04_coloriage-kawaii_1005006861918127 | W4: Coloriage kawaii magique à l'eau (enfant) | [Marque] | X4: magique à l'eau (enfant) — coloriage kawaii | [Marque] | Y4: magique à l'eau (enfant) : détente kawaii, illustrations mignonnes. Livraison rapide, avis vérifiés. Commandez sur [Marque] ! | Z4: <div class="product-desc"> <p>Coloriage kawaii <strong>« magique à l'eau (enfant) »</strong> — détente kawaii, illustrations mignonnes.</p> <p><strong>Envie de déconnecter et de vous détendre un crayon à la main ?</strong></p> <h3>✅ Une vraie parenthèse détente</h3> <p>Ce livre de kawaii aide à relâcher la pression : on se concentre sur les couleurs, le mental se pose. Idéal le soir ou le week-end.</p> <h3>✅ Des illustrations originales et mignonnes</h3> <p>Des pages au style kawaii, pensées pour être agréables à colorier du premier au dernier trait, sans motif trop chargé.</p> <h3>✅ Le cadeau qui fait toujours plaisir</h3> <p>Pour soi ou à offrir : un objet doux, accessible et personnel qui plaît aux ados comme aux adultes.</p> <h3>📦 Caractéristiques</h3> <ul> <li><strong>Type :</strong> Livre de coloriage broché</li> <li><strong>Pages :</strong> ≈ 24-30 pages</li> <li><strong>Papier :</strong> Épais, adapté aux feutres et crayons</li> <li><strong>Format :</strong> Compact, transportable</li> <li><strong>Contenu :</strong> 1 livre de coloriage</li> </ul> <h3>❓ Questions fréquentes</h3> <details><summary>Le papier bave-t-il avec les feutres ?</summary><p>Le papier est épais ; pour les feutres à alcool, glissez une feuille sous la page en cours par précaution.</p></details> <details><summary>Convient-il aux débutants ?</summary><p>Oui, les motifs sont accessibles : aucune technique requise, juste l'envie de colorier.</p></details> <details><summary>Y a-t-il du texte à l'intérieur ?</summary><p>Ce sont des pages à colorier ; le texte est minimal, l'univers est visuel.</p></details> <p><strong>🛒 Offrez-vous cette pause — Livraison offerte dès 39€ d'achat.</strong></p> </div>
A5: coloriage-kawaii-2 | B5: coloriage kawaii | C5: Livre de coloriage Cozy Japan (adulte, 28 p.) | D5: https://fr.aliexpress.com/item/1005009045159652.html | E5: 8.69 | F5: 0 | G5: =IF(OR(E5="",F5=""),"",E5+F5) | H5: =IFERROR(VLOOKUP(B5,'Collections'!$C$4:$L$18,10,FALSE),"") | I5: =IFERROR(H5/G5,"") | J5: 4.9 | K5: 5000 | L5: Choice — vendeur agrégé | M5: 16-19 juil. (~6-9 j) | N5: Choice | O5: Couleur Rose (28 pages) | P5: Coloriage anti-stress esthétique japonaise cozy — cadeau détente | Q5: Livre papier, visuels génériques (OK licence). Vérifier texte intérieur minimal (langue). Marge unité x2,9 (<x3), x3,4 en lot ≥2. | R5: Retenir | S5: 46213 | T5: AliExpress Choice ; livraison gratuite dès 10€ ; 1119 avis ; note agrégée | U5: PACKSHOT — E-commerce hero packshot of the coloring book «Livre de coloriage Cozy Japan (adulte, 28 p.)», cover facing forward, centered on a clean seamless pastel background, soft studio shadow, ultra-sharp, soft pastel kawaii brand aesthetic, cohesive palette (blush pink, cream, mint, lilac), 1:1 square. LIFESTYLE — Top-down flat-lay of «Livre de coloriage Cozy Japan (adulte, 28 p.)» on a cozy pastel desk with colored pencils, a warm drink and a small plush, soft natural morning light, hygge kawaii mood, soft pastel kawaii brand aesthetic, cohesive palette (blush pink, cream, mint, lilac), 1:1. EN SITUATION — Close-up of a person's hands coloring a kawaii page from «Livre de coloriage Cozy Japan (adulte, 28 p.)», cozy blanket, shallow depth of field, warm soft tones. DÉTAIL — Macro of the open inner pages of «Livre de coloriage Cozy Japan (adulte, 28 p.)» showing cute kawaii line-art illustrations, crisp lines, shallow depth of field. FEATURE — Clean product feature image of «Livre de coloriage Cozy Japan (adulte, 28 p.)» standing upright with minimal text callouts (page count, thick paper, anti-stress), soft pastel kawaii brand aesthetic, cohesive palette (blush pink, cream, mint, lilac), generous negative space for headline. | V5: .../outputs/coloriage-kawaii-arborescence-2026-07-09/images_produits/05_coloriage-kawaii_1005009045159652 | W5: Coloriage kawaii Cozy Japan (adulte, 28 p.) | [Marque] | X5: Cozy Japan (adulte, 28 p.) — coloriage kawaii | [Marque] | Y5: Cozy Japan (adulte, 28 p.) : détente kawaii, illustrations mignonnes. Livraison rapide, avis vérifiés. Commandez sur [Marque] ! | Z5: <div class="product-desc"> <p>Coloriage kawaii <strong>« Cozy Japan (adulte, 28 p.) »</strong> — détente kawaii, illustrations mignonnes.</p> <p><strong>Et si 15 minutes de coloriage remplaçaient le scroll du soir ?</strong></p> <h3>✅ Une vraie parenthèse détente</h3> <p>Ce livre de kawaii aide à relâcher la pression : on se concentre sur les couleurs, le mental se pose. Idéal le soir ou le week-end.</p> <h3>✅ Des illustrations originales et mignonnes</h3> <p>Des pages au style kawaii, pensées pour être agréables à colorier du premier au dernier trait, sans motif trop chargé.</p> <h3>✅ Le cadeau qui fait toujours plaisir</h3> <p>Pour soi ou à offrir : un objet doux, accessible et personnel qui plaît aux ados comme aux adultes.</p> <h3>📦 Caractéristiques</h3> <ul> <li><strong>Type :</strong> Livre de coloriage broché</li> <li><strong>Pages :</strong> 28 pages</li> <li><strong>Papier :</strong> Épais, adapté aux feutres et crayons</li> <li><strong>Format :</strong> Compact, transportable</li> <li><strong>Contenu :</strong> 1 livre de coloriage</li> </ul> <h3>❓ Questions fréquentes</h3> <details><summary>Le papier bave-t-il avec les feutres ?</summary><p>Le papier est épais ; pour les feutres à alcool, glissez une feuille sous la page en cours par précaution.</p></details> <details><summary>Convient-il aux débutants ?</summary><p>Oui, les motifs sont accessibles : aucune technique requise, juste l'envie de colorier.</p></details> <details><summary>Y a-t-il du texte à l'intérieur ?</summary><p>Ce sont des pages à colorier ; le texte est minimal, l'univers est visuel.</p></details> <p><strong>🛒 Offrez-vous cette pause — Livraison offerte dès 39€ d'achat.</strong></p> </div>
A6: coloriage-kawaii-3 | B6: coloriage kawaii | C6: Livre aquarelle portable 12 feuilles + pinceau | D6: https://fr.aliexpress.com/item/1005006863919029.html | E6: 4.59 | F6: 0 | G6: =IF(OR(E6="",F6=""),"",E6+F6) | H6: =IFERROR(VLOOKUP(B6,'Collections'!$C$4:$L$18,10,FALSE),"") | I6: =IFERROR(H6/G6,"") | J6: 4.9 | K6: 5000 | L6: Choice — vendeur agrégé | M6: 13-25 juil. (~3-15 j) | N6: Choice | O6: Fairytale Dreams (8 thèmes fantasy) | P6: Aquarelle nomade tout-en-un, 8 univers — enfants / débutants | Q6: Livre papier + pinceau + pastilles aquarelle : vérifier REACH pigments (contact enfant). Visuels génériques (OK). Délai jusqu'à ~15 j. | R6: Retenir | S6: 46213 | T6: AliExpress Choice ; prix Deal du Jour (base 4,61€) ; livraison gratuite dès 10€ ; 635 avis | U6: PACKSHOT — E-commerce hero packshot of the coloring book «Livre aquarelle portable 12 feuilles + pinceau», cover facing forward, centered on a clean seamless pastel background, soft studio shadow, ultra-sharp, soft pastel kawaii brand aesthetic, cohesive palette (blush pink, cream, mint, lilac), 1:1 square. LIFESTYLE — Top-down flat-lay of «Livre aquarelle portable 12 feuilles + pinceau» on a cozy pastel desk with colored pencils, a warm drink and a small plush, soft natural morning light, hygge kawaii mood, soft pastel kawaii brand aesthetic, cohesive palette (blush pink, cream, mint, lilac), 1:1. EN SITUATION — Close-up of a person's hands coloring a kawaii page from «Livre aquarelle portable 12 feuilles + pinceau», cozy blanket, shallow depth of field, warm soft tones. DÉTAIL — Macro of the open inner pages of «Livre aquarelle portable 12 feuilles + pinceau» showing cute kawaii line-art illustrations, crisp lines, shallow depth of field. FEATURE — Clean product feature image of «Livre aquarelle portable 12 feuilles + pinceau» standing upright with minimal text callouts (page count, thick paper, anti-stress), soft pastel kawaii brand aesthetic, cohesive palette (blush pink, cream, mint, lilac), generous negative space for headline. | V6: .../outputs/coloriage-kawaii-arborescence-2026-07-09/images_produits/06_coloriage-kawaii_1005006863919029 | W6: Coloriage kawaii aquarelle portable 12 feuilles + pinceau | [Marque] | X6: aquarelle portable 12 feuilles + pinceau — coloriage kawaii | Y6: aquarelle portable 12 feuilles + pinceau : détente kawaii, illustrations mignonnes. Livraison rapide, avis vérifiés. Commandez sur [Marque] ! | Z6: <div class="product-desc"> <p>Coloriage kawaii <strong>« aquarelle portable 12 feuilles + pinceau »</strong> — détente kawaii, illustrations mignonnes.</p> <p><strong>Besoin d'une pause créative, loin des écrans ?</strong></p> <h3>✅ Une vraie parenthèse détente</h3> <p>Ce livre de kawaii aide à relâcher la pression : on se concentre sur les couleurs, le mental se pose. Idéal le soir ou le week-end.</p> <h3>✅ Des illustrations originales et mignonnes</h3> <p>Des pages au style kawaii, pensées pour être agréables à colorier du premier au dernier trait, sans motif trop chargé.</p> <h3>✅ Le cadeau qui fait toujours plaisir</h3> <p>Pour soi ou à offrir : un objet doux, accessible et personnel qui plaît aux ados comme aux adultes.</p> <h3>📦 Caractéristiques</h3> <ul> <li><strong>Type :</strong> Livre de coloriage broché</li> <li><strong>Pages :</strong> ≈ 24-30 pages</li> <li><strong>Papier :</strong> Épais, adapté aux feutres et crayons</li> <li><strong>Format :</strong> Compact, transportable</li> <li><strong>Contenu :</strong> 1 livre de coloriage</li> </ul> <h3>❓ Questions fréquentes</h3> <details><summary>Le papier bave-t-il avec les feutres ?</summary><p>Le papier est épais ; pour les feutres à alcool, glissez une feuille sous la page en cours par précaution.</p></details> <details><summary>Convient-il aux débutants ?</summary><p>Oui, les motifs sont accessibles : aucune technique requise, juste l'envie de colorier.</p></details> <details><summary>Y a-t-il du texte à l'intérieur ?</summary><p>Ce sont des pages à colorier ; le texte est minimal, l'univers est visuel.</p></details> <p><strong>🛒 Offrez-vous cette pause — Livraison offerte dès 39€ d'achat.</strong></p> </div>
A7: coloriage-kawaii-4 | B7: coloriage kawaii | C7: Livre de coloriage Cozy Europe (adulte, 28 p.) | D7: https://fr.aliexpress.com/item/1005010439423261.html | E7: 7.59 | F7: 0 | G7: =IF(OR(E7="",F7=""),"",E7+F7) | H7: =IFERROR(VLOOKUP(B7,'Collections'!$C$4:$L$18,10,FALSE),"") | I7: =IFERROR(H7/G7,"") | J7: 4.9 | K7: 5000 | L7: Choice — vendeur agrégé | M7: 16-19 juil. (~6-9 j) | N7: Choice | O7: Style 8 (28 pages) | P7: Coloriage cozy adulte, scènes européennes mignonnes — détente / cadeau | Q7: Livre papier, visuels génériques (OK licence). Vérifier texte intérieur minimal. Marge x3,3. | R7: Retenir | S7: 46213 | T7: AliExpress Choice ; livraison gratuite dès 10€ ; 733 avis ; note agrégée | U7: PACKSHOT — E-commerce hero packshot of the coloring book «Livre de coloriage Cozy Europe (adulte, 28 p.)», cover facing forward, centered on a clean seamless pastel background, soft studio shadow, ultra-sharp, soft pastel kawaii brand aesthetic, cohesive palette (blush pink, cream, mint, lilac), 1:1 square. LIFESTYLE — Top-down flat-lay of «Livre de coloriage Cozy Europe (adulte, 28 p.)» on a cozy pastel desk with colored pencils, a warm drink and a small plush, soft natural morning light, hygge kawaii mood, soft pastel kawaii brand aesthetic, cohesive palette (blush pink, cream, mint, lilac), 1:1. EN SITUATION — Close-up of a person's hands coloring a kawaii page from «Livre de coloriage Cozy Europe (adulte, 28 p.)», cozy blanket, shallow depth of field, warm soft tones. DÉTAIL — Macro of the open inner pages of «Livre de coloriage Cozy Europe (adulte, 28 p.)» showing cute kawaii line-art illustrations, crisp lines, shallow depth of field. FEATURE — Clean product feature image of «Livre de coloriage Cozy Europe (adulte, 28 p.)» standing upright with minimal text callouts (page count, thick paper, anti-stress), soft pastel kawaii brand aesthetic, cohesive palette (blush pink, cream, mint, lilac), generous negative space for headline. | V7: .../outputs/coloriage-kawaii-arborescence-2026-07-09/images_produits/07_coloriage-kawaii_1005010439423261 | W7: Coloriage kawaii Cozy Europe (adulte, 28 p.) | [Marque] | X7: Cozy Europe (adulte, 28 p.) — coloriage kawaii | [Marque] | Y7: Cozy Europe (adulte, 28 p.) : détente kawaii, illustrations mignonnes. Livraison rapide, avis vérifiés. Commandez sur [Marque] ! | Z7: <div class="product-desc"> <p>Coloriage kawaii <strong>« Cozy Europe (adulte, 28 p.) »</strong> — détente kawaii, illustrations mignonnes.</p> <p><strong>Envie de déconnecter et de vous détendre un crayon à la main ?</strong></p> <h3>✅ Une vraie parenthèse détente</h3> <p>Ce livre de kawaii aide à relâcher la pression : on se concentre sur les couleurs, le mental se pose. Idéal le soir ou le week-end.</p> <h3>✅ Des illustrations originales et mignonnes</h3> <p>Des pages au style kawaii, pensées pour être agréables à colorier du premier au dernier trait, sans motif trop chargé.</p> <h3>✅ Le cadeau qui fait toujours plaisir</h3> <p>Pour soi ou à offrir : un objet doux, accessible et personnel qui plaît aux ados comme aux adultes.</p> <h3>📦 Caractéristiques</h3> <ul> <li><strong>Type :</strong> Livre de coloriage broché</li> <li><strong>Pages :</strong> 28 pages</li> <li><strong>Papier :</strong> Épais, adapté aux feutres et crayons</li> <li><strong>Format :</strong> Compact, transportable</li> <li><strong>Contenu :</strong> 1 livre de coloriage</li> </ul> <h3>❓ Questions fréquentes</h3> <details><summary>Le papier bave-t-il avec les feutres ?</summary><p>Le papier est épais ; pour les feutres à alcool, glissez une feuille sous la page en cours par précaution.</p></details> <details><summary>Convient-il aux débutants ?</summary><p>Oui, les motifs sont accessibles : aucune technique requise, juste l'envie de colorier.</p></details> <details><summary>Y a-t-il du texte à l'intérieur ?</summary><p>Ce sont des pages à colorier ; le texte est minimal, l'univers est visuel.</p></details> <p><strong>🛒 Offrez-vous cette pause — Livraison offerte dès 39€ d'achat.</strong></p> </div>
A8: coloriage-kawaii-5 | B8: coloriage kawaii | C8: Livre de coloriage Cat Moments (adulte, chats) | D8: https://fr.aliexpress.com/item/1005009054606907.html | E8: 6.89 | F8: 0 | G8: =IF(OR(E8="",F8=""),"",E8+F8) | H8: =IFERROR(VLOOKUP(B8,'Collections'!$C$4:$L$18,10,FALSE),"") | I8: =IFERROR(H8/G8,"") | J8: 4.9 | K8: 5000 | L8: Choice — vendeur agrégé | M8: 16-19 juil. (~6-9 j) | N8: Choice | O8: style 13 | P8: Pour amoureux des chats — coloriage relaxation, papier épais | Q8: Livre papier, visuels chats génériques (OK licence). Vérifier texte intérieur minimal. Marge x3,6. | R8: Retenir | S8: 46213 | T8: AliExpress Choice ; livraison gratuite dès 10€ ; 914 avis ; note agrégée | U8: PACKSHOT — E-commerce hero packshot of the coloring book «Livre de coloriage Cat Moments (adulte, chats)», cover facing forward, centered on a clean seamless pastel background, soft studio shadow, ultra-sharp, soft pastel kawaii brand aesthetic, cohesive palette (blush pink, cream, mint, lilac), 1:1 square. LIFESTYLE — Top-down flat-lay of «Livre de coloriage Cat Moments (adulte, chats)» on a cozy pastel desk with colored pencils, a warm drink and a small plush, soft natural morning light, hygge kawaii mood, soft pastel kawaii brand aesthetic, cohesive palette (blush pink, cream, mint, lilac), 1:1. EN SITUATION — Close-up of a person's hands coloring a kawaii page from «Livre de coloriage Cat Moments (adulte, chats)», cozy blanket, shallow depth of field, warm soft tones. DÉTAIL — Macro of the open inner pages of «Livre de coloriage Cat Moments (adulte, chats)» showing cute kawaii line-art illustrations, crisp lines, shallow depth of field. FEATURE — Clean product feature image of «Livre de coloriage Cat Moments (adulte, chats)» standing upright with minimal text callouts (page count, thick paper, anti-stress), soft pastel kawaii brand aesthetic, cohesive palette (blush pink, cream, mint, lilac), generous negative space for headline. | V8: .../outputs/coloriage-kawaii-arborescence-2026-07-09/images_produits/08_coloriage-kawaii_1005009054606907 | W8: Coloriage kawaii Cat Moments (adulte, chats) | [Marque] | X8: Cat Moments (adulte, chats) — coloriage kawaii | [Marque] | Y8: Cat Moments (adulte, chats) : détente kawaii, illustrations mignonnes. Livraison rapide, avis vérifiés. Commandez sur [Marque] ! | Z8: <div class="product-desc"> <p>Coloriage kawaii <strong>« Cat Moments (adulte, chats) »</strong> — détente kawaii, illustrations mignonnes.</p> <p><strong>Et si 15 minutes de coloriage remplaçaient le scroll du soir ?</strong></p> <h3>✅ Une vraie parenthèse détente</h3> <p>Ce livre de kawaii aide à relâcher la pression : on se concentre sur les couleurs, le mental se pose. Idéal le soir ou le week-end.</p> <h3>✅ Des illustrations originales et mignonnes</h3> <p>Des pages au style kawaii, pensées pour être agréables à colorier du premier au dernier trait, sans motif trop chargé.</p> <h3>✅ Le cadeau qui fait toujours plaisir</h3> <p>Pour soi ou à offrir : un objet doux, accessible et personnel qui plaît aux ados comme aux adultes.</p> <h3>📦 Caractéristiques</h3> <ul> <li><strong>Type :</strong> Livre de coloriage broché</li> <li><strong>Pages :</strong> ≈ 24-30 pages</li> <li><strong>Papier :</strong> Épais, adapté aux feutres et crayons</li> <li><strong>Format :</strong> Compact, transportable</li> <li><strong>Contenu :</strong> 1 livre de coloriage</li> </ul> <h3>❓ Questions fréquentes</h3> <details><summary>Le papier bave-t-il avec les feutres ?</summary><p>Le papier est épais ; pour les feutres à alcool, glissez une feuille sous la page en cours par précaution.</p></details> <details><summary>Convient-il aux débutants ?</summary><p>Oui, les motifs sont accessibles : aucune technique requise, juste l'envie de colorier.</p></details> <details><summary>Y a-t-il du texte à l'intérieur ?</summary><p>Ce sont des pages à colorier ; le texte est minimal, l'univers est visuel.</p></details> <p><strong>🛒 Offrez-vous cette pause — Livraison offerte dès 39€ d'achat.</strong></p> </div>
A9: coloriage-adulte-1 | B9: coloriage adulte | C9: Coloriage relaxation — pages à colorier & à dessiner | D9: https://fr.aliexpress.com/item/1005010376474304.html | E9: 5.69 | F9: 0 | G9: =IF(OR(E9="",F9=""),"",E9+F9) | H9: =IFERROR(VLOOKUP(B9,'Collections'!$C$4:$L$18,10,FALSE),"") | I9: =IFERROR(H9/G9,"") | J9: 4.9 | K9: 5000 | L9: Choice — vendeur agrégé | M9: 16-19 juil. (~6-9 j) | N9: Choice | O9: Couleur: 1PCS-Random | P9: Coloriage relaxation anti-stress, colorier + dessiner | Q9: Livre papier, visuels génériques (OK licence). Vérifier texte intérieur minimal (langue). | R9: Retenir | S9: 46213 | T9: AliExpress Choice ; livraison gratuite dès 10€ ; note agrégée multi-vendeurs | U9: PACKSHOT — E-commerce hero packshot of the coloring book «Coloriage relaxation — pages à colorier & à dessiner», cover facing forward, centered on a clean seamless pastel background, soft studio shadow, ultra-sharp, soft pastel kawaii brand aesthetic, cohesive palette (blush pink, cream, mint, lilac), 1:1 square. LIFESTYLE — Top-down flat-lay of «Coloriage relaxation — pages à colorier & à dessiner» on a cozy pastel desk with colored pencils, a warm drink and a small plush, soft natural morning light, hygge kawaii mood, soft pastel kawaii brand aesthetic, cohesive palette (blush pink, cream, mint, lilac), 1:1. EN SITUATION — Close-up of a person's hands coloring a cozy anti-stress page from «Coloriage relaxation — pages à colorier & à dessiner», cozy blanket, shallow depth of field, warm soft tones. DÉTAIL — Macro of the open inner pages of «Coloriage relaxation — pages à colorier & à dessiner» showing cute cozy anti-stress line-art illustrations, crisp lines, shallow depth of field. FEATURE — Clean product feature image of «Coloriage relaxation — pages à colorier & à dessiner» standing upright with minimal text callouts (page count, thick paper, anti-stress), soft pastel kawaii brand aesthetic, cohesive palette (blush pink, cream, mint, lilac), generous negative space for headline. | V9: .../outputs/coloriage-kawaii-arborescence-2026-07-09/images_produits/09_coloriage-adulte_1005010376474304 | W9: Coloriage adulte relaxation — pages à colorier & à dessin | [Marque] | X9: relaxation — pages à colorier & à dessin — coloriage adulte | Y9: relaxation — pages à colorier & à dessin : anti-stress, papier épais. Livraison rapide, avis vérifiés. Commandez sur [Marque] ! | Z9: <div class="product-desc"> <p>Coloriage adulte <strong>« relaxation — pages à colorier &amp; à dessin »</strong> — anti-stress, papier épais.</p> <p><strong>Envie de déconnecter et de vous détendre un crayon à la main ?</strong></p> <h3>✅ Une vraie parenthèse détente</h3> <p>Ce livre de anti-stress aide à relâcher la pression : on se concentre sur les couleurs, le mental se pose. Idéal le soir ou le week-end.</p> <h3>✅ Des illustrations originales et mignonnes</h3> <p>Des pages au style anti-stress, pensées pour être agréables à colorier du premier au dernier trait, sans motif trop chargé.</p> <h3>✅ Le cadeau qui fait toujours plaisir</h3> <p>Pour soi ou à offrir : un objet doux, accessible et personnel qui plaît aux ados comme aux adultes.</p> <h3>📦 Caractéristiques</h3> <ul> <li><strong>Type :</strong> Livre de coloriage broché</li> <li><strong>Pages :</strong> ≈ 24-30 pages</li> <li><strong>Papier :</strong> Épais, adapté aux feutres et crayons</li> <li><strong>Format :</strong> Compact, transportable</li> <li><strong>Contenu :</strong> 1 livre de coloriage</li> </ul> <h3>❓ Questions fréquentes</h3> <details><summary>Le papier bave-t-il avec les feutres ?</summary><p>Le papier est épais ; pour les feutres à alcool, glissez une feuille sous la page en cours par précaution.</p></details> <details><summary>Convient-il aux débutants ?</summary><p>Oui, les motifs sont accessibles : aucune technique requise, juste l'envie de colorier.</p></details> <details><summary>Y a-t-il du texte à l'intérieur ?</summary><p>Ce sont des pages à colorier ; le texte est minimal, l'univers est visuel.</p></details> <p><strong>🛒 Offrez-vous cette pause — Livraison offerte dès 39€ d'achat.</strong></p> </div>
A10: coloriage-adulte-2 | B10: coloriage adulte | C10: Coloriage adulte motifs audacieux & faciles | D10: https://fr.aliexpress.com/item/1005009384551175.html | E10: 6.69 | F10: 0 | G10: =IF(OR(E10="",F10=""),"",E10+F10) | H10: =IFERROR(VLOOKUP(B10,'Collections'!$C$4:$L$18,10,FALSE),"") | I10: =IFERROR(H10/G10,"") | J10: 4.9 | K10: 4000 | L10: Choice — vendeur agrégé | M10: 16-19 juil. (~6-9 j) | N10: Choice | O10: Couleur: MULTI | P10: Bold & easy : gros motifs faciles, anti-stress accessible | Q10: Livre papier, visuels génériques (OK licence). Vérifier texte intérieur minimal (langue). | R10: Retenir | S10: 46213 | T10: AliExpress Choice ; livraison gratuite dès 10€ ; note agrégée multi-vendeurs | U10: PACKSHOT — E-commerce hero packshot of the coloring book «Coloriage adulte motifs audacieux & faciles», cover facing forward, centered on a clean seamless pastel background, soft studio shadow, ultra-sharp, soft pastel kawaii brand aesthetic, cohesive palette (blush pink, cream, mint, lilac), 1:1 square. LIFESTYLE — Top-down flat-lay of «Coloriage adulte motifs audacieux & faciles» on a cozy pastel desk with colored pencils, a warm drink and a small plush, soft natural morning light, hygge kawaii mood, soft pastel kawaii brand aesthetic, cohesive palette (blush pink, cream, mint, lilac), 1:1. EN SITUATION — Close-up of a person's hands coloring a cozy anti-stress page from «Coloriage adulte motifs audacieux & faciles», cozy blanket, shallow depth of field, warm soft tones. DÉTAIL — Macro of the open inner pages of «Coloriage adulte motifs audacieux & faciles» showing cute cozy anti-stress line-art illustrations, crisp lines, shallow depth of field. FEATURE — Clean product feature image of «Coloriage adulte motifs audacieux & faciles» standing upright with minimal text callouts (page count, thick paper, anti-stress), soft pastel kawaii brand aesthetic, cohesive palette (blush pink, cream, mint, lilac), generous negative space for headline. | V10: .../outputs/coloriage-kawaii-arborescence-2026-07-09/images_produits/10_coloriage-adulte_1005009384551175 | W10: Coloriage adulte adulte motifs audacieux & faciles | [Marque] | X10: adulte motifs audacieux & faciles — coloriage adulte | [Mar | Y10: adulte motifs audacieux & faciles : anti-stress, papier épais. Livraison rapide, avis vérifiés. Commandez sur [Marque] ! | Z10: <div class="product-desc"> <p>Coloriage adulte <strong>« adulte motifs audacieux &amp; faciles »</strong> — anti-stress, papier épais.</p> <p><strong>Et si 15 minutes de coloriage remplaçaient le scroll du soir ?</strong></p> <h3>✅ Une vraie parenthèse détente</h3> <p>Ce livre de anti-stress aide à relâcher la pression : on se concentre sur les couleurs, le mental se pose. Idéal le soir ou le week-end.</p> <h3>✅ Des illustrations originales et mignonnes</h3> <p>Des pages au style anti-stress, pensées pour être agréables à colorier du premier au dernier trait, sans motif trop chargé.</p> <h3>✅ Le cadeau qui fait toujours plaisir</h3> <p>Pour soi ou à offrir : un objet doux, accessible et personnel qui plaît aux ados comme aux adultes.</p> <h3>📦 Caractéristiques</h3> <ul> <li><strong>Type :</strong> Livre de coloriage broché</li> <li><strong>Pages :</strong> ≈ 24-30 pages</li> <li><strong>Papier :</strong> Épais, adapté aux feutres et crayons</li> <li><strong>Format :</strong> Compact, transportable</li> <li><strong>Contenu :</strong> 1 livre de coloriage</li> </ul> <h3>❓ Questions fréquentes</h3> <details><summary>Le papier bave-t-il avec les feutres ?</summary><p>Le papier est épais ; pour les feutres à alcool, glissez une feuille sous la page en cours par précaution.</p></details> <details><summary>Convient-il aux débutants ?</summary><p>Oui, les motifs sont accessibles : aucune technique requise, juste l'envie de colorier.</p></details> <details><summary>Y a-t-il du texte à l'intérieur ?</summary><p>Ce sont des pages à colorier ; le texte est minimal, l'univers est visuel.</p></details> <p><strong>🛒 Offrez-vous cette pause — Livraison offerte dès 39€ d'achat.</strong></p> </div>
A11: coloriage-adulte-3 | B11: coloriage adulte | C11: Coloriage adulte thème chat (relaxation) | D11: https://fr.aliexpress.com/item/1005008909041175.html | E11: 6.49 | F11: 0 | G11: =IF(OR(E11="",F11=""),"",E11+F11) | H11: =IFERROR(VLOOKUP(B11,'Collections'!$C$4:$L$18,10,FALSE),"") | I11: =IFERROR(H11/G11,"") | J11: 4.9 | K11: 3000 | L11: Choice — vendeur agrégé | M11: 16-19 juil. (~6-9 j) | N11: Choice | O11: Color: StyleA (China Mainland) | P11: Coloriage chats relaxation — cat-lovers adultes | Q11: Livre papier, visuels génériques (OK licence). Vérifier texte intérieur minimal (langue). | R11: Retenir | S11: 46213 | T11: AliExpress Choice ; livraison gratuite dès 10€ ; note agrégée multi-vendeurs | U11: PACKSHOT — E-commerce hero packshot of the coloring book «Coloriage adulte thème chat (relaxation)», cover facing forward, centered on a clean seamless pastel background, soft studio shadow, ultra-sharp, soft pastel kawaii brand aesthetic, cohesive palette (blush pink, cream, mint, lilac), 1:1 square. LIFESTYLE — Top-down flat-lay of «Coloriage adulte thème chat (relaxation)» on a cozy pastel desk with colored pencils, a warm drink and a small plush, soft natural morning light, hygge kawaii mood, soft pastel kawaii brand aesthetic, cohesive palette (blush pink, cream, mint, lilac), 1:1. EN SITUATION — Close-up of a person's hands coloring a cozy anti-stress page from «Coloriage adulte thème chat (relaxation)», cozy blanket, shallow depth of field, warm soft tones. DÉTAIL — Macro of the open inner pages of «Coloriage adulte thème chat (relaxation)» showing cute cozy anti-stress line-art illustrations, crisp lines, shallow depth of field. FEATURE — Clean product feature image of «Coloriage adulte thème chat (relaxation)» standing upright with minimal text callouts (page count, thick paper, anti-stress), soft pastel kawaii brand aesthetic, cohesive palette (blush pink, cream, mint, lilac), generous negative space for headline. | V11: .../outputs/coloriage-kawaii-arborescence-2026-07-09/images_produits/11_coloriage-adulte_1005008909041175 | W11: Coloriage adulte adulte thème chat (relaxation) | [Marque] | X11: adulte thème chat (relaxation) — coloriage adulte | [Marque | Y11: adulte thème chat (relaxation) : anti-stress, papier épais. Livraison rapide, avis vérifiés. Commandez sur [Marque] ! | Z11: <div class="product-desc"> <p>Coloriage adulte <strong>« adulte thème chat (relaxation) »</strong> — anti-stress, papier épais.</p> <p><strong>Besoin d'une pause créative, loin des écrans ?</strong></p> <h3>✅ Une vraie parenthèse détente</h3> <p>Ce livre de anti-stress aide à relâcher la pression : on se concentre sur les couleurs, le mental se pose. Idéal le soir ou le week-end.</p> <h3>✅ Des illustrations originales et mignonnes</h3> <p>Des pages au style anti-stress, pensées pour être agréables à colorier du premier au dernier trait, sans motif trop chargé.</p> <h3>✅ Le cadeau qui fait toujours plaisir</h3> <p>Pour soi ou à offrir : un objet doux, accessible et personnel qui plaît aux ados comme aux adultes.</p> <h3>📦 Caractéristiques</h3> <ul> <li><strong>Type :</strong> Livre de coloriage broché</li> <li><strong>Pages :</strong> ≈ 24-30 pages</li> <li><strong>Papier :</strong> Épais, adapté aux feutres et crayons</li> <li><strong>Format :</strong> Compact, transportable</li> <li><strong>Contenu :</strong> 1 livre de coloriage</li> </ul> <h3>❓ Questions fréquentes</h3> <details><summary>Le papier bave-t-il avec les feutres ?</summary><p>Le papier est épais ; pour les feutres à alcool, glissez une feuille sous la page en cours par précaution.</p></details> <details><summary>Convient-il aux débutants ?</summary><p>Oui, les motifs sont accessibles : aucune technique requise, juste l'envie de colorier.</p></details> <details><summary>Y a-t-il du texte à l'intérieur ?</summary><p>Ce sont des pages à colorier ; le texte est minimal, l'univers est visuel.</p></details> <p><strong>🛒 Offrez-vous cette pause — Livraison offerte dès 39€ d'achat.</strong></p> </div>
A12: coloriage-adulte-4 | B12: coloriage adulte | C12: Coloriage adulte graffitis / street | D12: https://fr.aliexpress.com/item/1005008666823092.html | E12: 6.49 | F12: 0 | G12: =IF(OR(E12="",F12=""),"",E12+F12) | H12: =IFERROR(VLOOKUP(B12,'Collections'!$C$4:$L$18,10,FALSE),"") | I12: =IFERROR(H12/G12,"") | J12: 4.9 | K12: 2000 | L12: Choice — vendeur agrégé | M12: 16-19 juil. (~6-9 j) | N12: Choice | O12: Couleur: MULTI | P12: Coloriage street/graffiti adulte — style urbain | Q12: Livre papier, visuels génériques (OK licence). Vérifier texte intérieur minimal (langue). | R12: Retenir | S12: 46213 | T12: AliExpress Choice ; livraison gratuite dès 10€ ; note agrégée multi-vendeurs | U12: PACKSHOT — E-commerce hero packshot of the coloring book «Coloriage adulte graffitis / street», cover facing forward, centered on a clean seamless pastel background, soft studio shadow, ultra-sharp, soft pastel kawaii brand aesthetic, cohesive palette (blush pink, cream, mint, lilac), 1:1 square. LIFESTYLE — Top-down flat-lay of «Coloriage adulte graffitis / street» on a cozy pastel desk with colored pencils, a warm drink and a small plush, soft natural morning light, hygge kawaii mood, soft pastel kawaii brand aesthetic, cohesive palette (blush pink, cream, mint, lilac), 1:1. EN SITUATION — Close-up of a person's hands coloring a cozy anti-stress page from «Coloriage adulte graffitis / street», cozy blanket, shallow depth of field, warm soft tones. DÉTAIL — Macro of the open inner pages of «Coloriage adulte graffitis / street» showing cute cozy anti-stress line-art illustrations, crisp lines, shallow depth of field. FEATURE — Clean product feature image of «Coloriage adulte graffitis / street» standing upright with minimal text callouts (page count, thick paper, anti-stress), soft pastel kawaii brand aesthetic, cohesive palette (blush pink, cream, mint, lilac), generous negative space for headline. | V12: .../outputs/coloriage-kawaii-arborescence-2026-07-09/images_produits/12_coloriage-adulte_1005008666823092 | W12: Coloriage adulte adulte graffitis / street | [Marque] | X12: adulte graffitis / street — coloriage adulte | [Marque] | Y12: adulte graffitis / street : anti-stress, papier épais. Livraison rapide, avis vérifiés. Commandez sur [Marque] ! | Z12: <div class="product-desc"> <p>Coloriage adulte <strong>« adulte graffitis / street »</strong> — anti-stress, papier épais.</p> <p><strong>Envie de déconnecter et de vous détendre un crayon à la main ?</strong></p> <h3>✅ Une vraie parenthèse détente</h3> <p>Ce livre de anti-stress aide à relâcher la pression : on se concentre sur les couleurs, le mental se pose. Idéal le soir ou le week-end.</p> <h3>✅ Des illustrations originales et mignonnes</h3> <p>Des pages au style anti-stress, pensées pour être agréables à colorier du premier au dernier trait, sans motif trop chargé.</p> <h3>✅ Le cadeau qui fait toujours plaisir</h3> <p>Pour soi ou à offrir : un objet doux, accessible et personnel qui plaît aux ados comme aux adultes.</p> <h3>📦 Caractéristiques</h3> <ul> <li><strong>Type :</strong> Livre de coloriage broché</li> <li><strong>Pages :</strong> ≈ 24-30 pages</li> <li><strong>Papier :</strong> Épais, adapté aux feutres et crayons</li> <li><strong>Format :</strong> Compact, transportable</li> <li><strong>Contenu :</strong> 1 livre de coloriage</li> </ul> <h3>❓ Questions fréquentes</h3> <details><summary>Le papier bave-t-il avec les feutres ?</summary><p>Le papier est épais ; pour les feutres à alcool, glissez une feuille sous la page en cours par précaution.</p></details> <details><summary>Convient-il aux débutants ?</summary><p>Oui, les motifs sont accessibles : aucune technique requise, juste l'envie de colorier.</p></details> <details><summary>Y a-t-il du texte à l'intérieur ?</summary><p>Ce sont des pages à colorier ; le texte est minimal, l'univers est visuel.</p></details> <p><strong>🛒 Offrez-vous cette pause — Livraison offerte dès 39€ d'achat.</strong></p> </div>
A13: coloriage-adulte-5 | B13: coloriage adulte | C13: Coloriage adulte mignon & simple | D13: https://fr.aliexpress.com/item/1005008908845958.html | E13: 6.79 | F13: 0 | G13: =IF(OR(E13="",F13=""),"",E13+F13) | H13: =IFERROR(VLOOKUP(B13,'Collections'!$C$4:$L$18,10,FALSE),"") | I13: =IFERROR(H13/G13,"") | J13: 4.9 | K13: 2000 | L13: Choice — vendeur agrégé | M13: 16-19 juil. (~6-9 j) | N13: Choice | O13: Couleur: MULTI | P13: Coloriage mignon & simple, motifs faciles détente | Q13: Livre papier, visuels génériques (OK licence). Vérifier texte intérieur minimal (langue). | R13: Retenir | S13: 46213 | T13: AliExpress Choice ; livraison gratuite dès 10€ ; note agrégée multi-vendeurs | U13: PACKSHOT — E-commerce hero packshot of the coloring book «Coloriage adulte mignon & simple», cover facing forward, centered on a clean seamless pastel background, soft studio shadow, ultra-sharp, soft pastel kawaii brand aesthetic, cohesive palette (blush pink, cream, mint, lilac), 1:1 square. LIFESTYLE — Top-down flat-lay of «Coloriage adulte mignon & simple» on a cozy pastel desk with colored pencils, a warm drink and a small plush, soft natural morning light, hygge kawaii mood, soft pastel kawaii brand aesthetic, cohesive palette (blush pink, cream, mint, lilac), 1:1. EN SITUATION — Close-up of a person's hands coloring a cozy anti-stress page from «Coloriage adulte mignon & simple», cozy blanket, shallow depth of field, warm soft tones. DÉTAIL — Macro of the open inner pages of «Coloriage adulte mignon & simple» showing cute cozy anti-stress line-art illustrations, crisp lines, shallow depth of field. FEATURE — Clean product feature image of «Coloriage adulte mignon & simple» standing upright with minimal text callouts (page count, thick paper, anti-stress), soft pastel kawaii brand aesthetic, cohesive palette (blush pink, cream, mint, lilac), generous negative space for headline. | V13: .../outputs/coloriage-kawaii-arborescence-2026-07-09/images_produits/13_coloriage-adulte_1005008908845958 | W13: Coloriage adulte adulte mignon & simple | [Marque] | X13: adulte mignon & simple — coloriage adulte | [Marque] | Y13: adulte mignon & simple : anti-stress, papier épais. Livraison rapide, avis vérifiés. Commandez sur [Marque] ! | Z13: <div class="product-desc"> <p>Coloriage adulte <strong>« adulte mignon &amp; simple »</strong> — anti-stress, papier épais.</p> <p><strong>Et si 15 minutes de coloriage remplaçaient le scroll du soir ?</strong></p> <h3>✅ Une vraie parenthèse détente</h3> <p>Ce livre de anti-stress aide à relâcher la pression : on se concentre sur les couleurs, le mental se pose. Idéal le soir ou le week-end.</p> <h3>✅ Des illustrations originales et mignonnes</h3> <p>Des pages au style anti-stress, pensées pour être agréables à colorier du premier au dernier trait, sans motif trop chargé.</p> <h3>✅ Le cadeau qui fait toujours plaisir</h3> <p>Pour soi ou à offrir : un objet doux, accessible et personnel qui plaît aux ados comme aux adultes.</p> <h3>📦 Caractéristiques</h3> <ul> <li><strong>Type :</strong> Livre de coloriage broché</li> <li><strong>Pages :</strong> ≈ 24-30 pages</li> <li><strong>Papier :</strong> Épais, adapté aux feutres et crayons</li> <li><strong>Format :</strong> Compact, transportable</li> <li><strong>Contenu :</strong> 1 livre de coloriage</li> </ul> <h3>❓ Questions fréquentes</h3> <details><summary>Le papier bave-t-il avec les feutres ?</summary><p>Le papier est épais ; pour les feutres à alcool, glissez une feuille sous la page en cours par précaution.</p></details> <details><summary>Convient-il aux débutants ?</summary><p>Oui, les motifs sont accessibles : aucune technique requise, juste l'envie de colorier.</p></details> <details><summary>Y a-t-il du texte à l'intérieur ?</summary><p>Ce sont des pages à colorier ; le texte est minimal, l'univers est visuel.</p></details> <p><strong>🛒 Offrez-vous cette pause — Livraison offerte dès 39€ d'achat.</strong></p> </div>
A14: coloriage-magique-1 | B14: coloriage magique | C14: Coloriage magique à l'eau réutilisable (enfant) | D14: https://fr.aliexpress.com/item/1005007170687871.html | E14: 4.29 | F14: 0 | G14: =IF(OR(E14="",F14=""),"",E14+F14) | H14: =IFERROR(VLOOKUP(B14,'Collections'!$C$4:$L$18,10,FALSE),"") | I14: =IFERROR(H14/G14,"") | J14: 4.9 | K14: 10000 | L14: Choice — vendeur agrégé | M14: 18-23 juil. (~8-13 j) | N14: Choice | O14: Couleur: 1pc pen random | P14: Coloriage à l'eau sans tache & réutilisable — cadeau enfant | Q14: JOUET ENFANT : conformité CE/EN71 + GPSR requise ; risque suffocation (petites pièces) ; exiger docs conformité fournisseur. Visuels génériques (OK licence). | R14: Retenir | S14: 46213 | T14: AliExpress Choice ; livraison gratuite dès 10€ ; note agrégée | U14: PACKSHOT — Hero packshot of the kids activity product «Coloriage magique à l'eau réutilisable (enfant)» (magic water / reusable), centered on clean bright pastel background, soft shadow, ultra-sharp, soft pastel kawaii brand aesthetic, cohesive palette (blush pink, cream, mint, lilac), 1:1. LIFESTYLE — A happy child using «Coloriage magique à l'eau réutilisable (enfant)» at a bright playful table, colorful, safe, soft daylight, top-down, soft pastel kawaii brand aesthetic, cohesive palette (blush pink, cream, mint, lilac), 1:1. EN SITUATION — Close-up of little hands revealing colors on a kids magic-water page of «Coloriage magique à l'eau réutilisable (enfant)», joyful, shallow depth of field. DÉTAIL — Macro of «Coloriage magique à l'eau réutilisable (enfant)» pages and the water pen, cute kids magic-water illustrations, crisp, colorful. FEATURE — Clean feature image of «Coloriage magique à l'eau réutilisable (enfant)» with playful callouts (no mess, reusable, ages 3+), pastel palette, negative space. | V14: .../outputs/coloriage-kawaii-arborescence-2026-07-09/images_produits/14_coloriage-magique_1005007170687871 | W14: Coloriage magique magique à l'eau réutilisable (enfant) | [Marque] | X14: magique à l'eau réutilisable (enfant) — coloriage magique | | Y14: magique à l'eau réutilisable (enfant) : à l'eau, réutilisable, sans tache. Livraison rapide, avis vérifiés. Commandez sur [Marque] ! | Z14: <div class="product-desc"> <p>Coloriage magique <strong>« magique à l'eau réutilisable (enfant) »</strong> — à l'eau, réutilisable, sans tache.</p> <p><strong>Occuper les enfants sans dégât ni écran, c'est possible ?</strong></p> <h3>✅ Zéro tache, 100% amusement</h3> <p>Coloriage à l'eau : l'enfant peint avec de l'eau, les couleurs apparaissent, puis s'effacent en séchant — réutilisable à l'infini.</p> <h3>✅ Développe créativité et concentration</h3> <p>Une activité calme qui occupe les enfants intelligemment, à la maison comme en voyage.</p> <h3>✅ Cadeau malin et abordable</h3> <p>Parfait pour un anniversaire ou une occupation de vacances, à un prix doux.</p> <h3>📦 Caractéristiques</h3> <ul> <li><strong>Type :</strong> Livre magique à l'eau réutilisable</li> <li><strong>Âge conseillé :</strong> Dès 3 ans (petites pièces : sous surveillance)</li> <li><strong>Contenu :</strong> 1 livre + 1 stylo à eau</li> <li><strong>Illustrations :</strong> Génériques et mignonnes</li> <li><strong>Entretien :</strong> Sèche et se réutilise</li> </ul> <h3>❓ Questions fréquentes</h3> <details><summary>À partir de quel âge ?</summary><p>Conseillé dès 3 ans ; les tout-petits sous la surveillance d'un adulte (petites pièces).</p></details> <details><summary>C'est vraiment réutilisable ?</summary><p>Oui : une fois sec, le livre redevient blanc et se recolorie.</p></details> <details><summary>Le produit est-il sûr ?</summary><p>Vérifiez toujours la conformité CE/EN71 ; à utiliser sous surveillance pour les plus jeunes.</p></details> <p><strong>🛒 Faites plaisir à votre enfant — Livraison offerte dès 39€ d'achat.</strong></p> </div>
A15: coloriage-magique-2 | B15: coloriage magique | C15: Livre peinture à l'eau magique (enfant) | D15: https://fr.aliexpress.com/item/1005010530716815.html | E15: 4.39 | F15: 0 | G15: =IF(OR(E15="",F15=""),"",E15+F15) | H15: =IFERROR(VLOOKUP(B15,'Collections'!$C$4:$L$18,10,FALSE),"") | I15: =IFERROR(H15/G15,"") | J15: 4.9 | K15: 10000 | L15: Choice — vendeur agrégé | M15: 16-19 juil. (~6-9 j) | N15: Choice | O15: Couleur: 1pc pen random | P15: Peinture à l'eau magique réutilisable — enfant / voyage | Q15: JOUET ENFANT : conformité CE/EN71 + GPSR requise ; risque suffocation (petites pièces) ; exiger docs conformité fournisseur. Visuels génériques (OK licence). | R15: Retenir | S15: 46213 | T15: AliExpress Choice ; livraison gratuite dès 10€ ; note agrégée | U15: PACKSHOT — Hero packshot of the kids activity product «Livre peinture à l'eau magique (enfant)» (magic water / reusable), centered on clean bright pastel background, soft shadow, ultra-sharp, soft pastel kawaii brand aesthetic, cohesive palette (blush pink, cream, mint, lilac), 1:1. LIFESTYLE — A happy child using «Livre peinture à l'eau magique (enfant)» at a bright playful table, colorful, safe, soft daylight, top-down, soft pastel kawaii brand aesthetic, cohesive palette (blush pink, cream, mint, lilac), 1:1. EN SITUATION — Close-up of little hands revealing colors on a kids magic-water page of «Livre peinture à l'eau magique (enfant)», joyful, shallow depth of field. DÉTAIL — Macro of «Livre peinture à l'eau magique (enfant)» pages and the water pen, cute kids magic-water illustrations, crisp, colorful. FEATURE — Clean feature image of «Livre peinture à l'eau magique (enfant)» with playful callouts (no mess, reusable, ages 3+), pastel palette, negative space. | V15: .../outputs/coloriage-kawaii-arborescence-2026-07-09/images_produits/15_coloriage-magique_1005010530716815 | W15: Coloriage magique peinture à l'eau magique (enfant) | [Marque] | X15: peinture à l'eau magique (enfant) — coloriage magique | [Ma | Y15: peinture à l'eau magique (enfant) : à l'eau, réutilisable, sans tache. Livraison rapide, avis vérifiés. Commandez sur [Marque] ! | Z15: <div class="product-desc"> <p>Coloriage magique <strong>« peinture à l'eau magique (enfant) »</strong> — à l'eau, réutilisable, sans tache.</p> <p><strong>Un cadeau créatif qui plaît vraiment aux enfants ?</strong></p> <h3>✅ Zéro tache, 100% amusement</h3> <p>Coloriage à l'eau : l'enfant peint avec de l'eau, les couleurs apparaissent, puis s'effacent en séchant — réutilisable à l'infini.</p> <h3>✅ Développe créativité et concentration</h3> <p>Une activité calme qui occupe les enfants intelligemment, à la maison comme en voyage.</p> <h3>✅ Cadeau malin et abordable</h3> <p>Parfait pour un anniversaire ou une occupation de vacances, à un prix doux.</p> <h3>📦 Caractéristiques</h3> <ul> <li><strong>Type :</strong> Livre magique à l'eau réutilisable</li> <li><strong>Âge conseillé :</strong> Dès 3 ans (petites pièces : sous surveillance)</li> <li><strong>Contenu :</strong> 1 livre + 1 stylo à eau</li> <li><strong>Illustrations :</strong> Génériques et mignonnes</li> <li><strong>Entretien :</strong> Sèche et se réutilise</li> </ul> <h3>❓ Questions fréquentes</h3> <details><summary>À partir de quel âge ?</summary><p>Conseillé dès 3 ans ; les tout-petits sous la surveillance d'un adulte (petites pièces).</p></details> <details><summary>C'est vraiment réutilisable ?</summary><p>Oui : une fois sec, le livre redevient blanc et se recolorie.</p></details> <details><summary>Le produit est-il sûr ?</summary><p>Vérifiez toujours la conformité CE/EN71 ; à utiliser sous surveillance pour les plus jeunes.</p></details> <p><strong>🛒 Faites plaisir à votre enfant — Livraison offerte dès 39€ d'achat.</strong></p> </div>
... A33: coloriage-manga-5 | B33: coloriage manga | C33: Cahier technique dessin manga débutants | D33: https://fr.aliexpress.com/item/1005008557835900.html | E33: 6.89 | F33: 0 | G33: =IF(OR(E33="",F33=""),"",E33+F33) | H33: =IFERROR(VLOOKUP(B33,'Collections'!$C$4:$L$18,10,FALSE),"") | I33: =IFERROR(H33/G33,"") | J33: 4.9 | K33: 700 | L33: Choice — vendeur agrégé | M33: 16-19 juil. (~6-9 j) | N33: Choice | O33: Couleur: 1Book J | P33: Cahier technique dessin manga — copie de lignes débutant | Q33: Livre papier style anime générique. VÉRIFIER visuels : AUCUN personnage sous licence (Naruto/One Piece/Demon Slayer...). Texte intérieur minimal (langue). | R33: Retenir | S33: 46213 | T33: AliExpress Choice ; livraison gratuite dès 10€ ; note agrégée | U33: PACKSHOT — E-commerce hero packshot of the coloring book «Cahier technique dessin manga débutants», cover facing forward, centered on a clean seamless pastel background, soft studio shadow, ultra-sharp, soft pastel kawaii brand aesthetic, cohesive palette (blush pink, cream, mint, lilac), 1:1 square. LIFESTYLE — Top-down flat-lay of «Cahier technique dessin manga débutants» on a cozy pastel desk with colored pencils, a warm drink and a small plush, soft natural morning light, hygge kawaii mood, soft pastel kawaii brand aesthetic, cohesive palette (blush pink, cream, mint, lilac), 1:1. EN SITUATION — Close-up of a person's hands coloring a anime-style page from «Cahier technique dessin manga débutants», cozy blanket, shallow depth of field, warm soft tones. DÉTAIL — Macro of the open inner pages of «Cahier technique dessin manga débutants» showing cute anime-style line-art illustrations, crisp lines, shallow depth of field. FEATURE — Clean product feature image of «Cahier technique dessin manga débutants» standing upright with minimal text callouts (page count, thick paper, anti-stress), soft pastel kawaii brand aesthetic, cohesive palette (blush pink, cream, mint, lilac), generous negative space for headline. | V33: .../outputs/coloriage-kawaii-arborescence-2026-07-09/images_produits/33_coloriage-manga_1005008557835900 | W33: Coloriage manga Cahier technique dessin manga débutants | [Marque] | X33: Cahier technique dessin manga débutants — coloriage manga | | Y33: Cahier technique dessin manga débutants : style anime, apprendre à dessiner. Livraison rapide, avis vérifiés. Commandez sur [Marque] ! | Z33: <div class="product-desc"> <p>Coloriage manga <strong>« Cahier technique dessin manga débutants »</strong> — style anime, apprendre à dessiner.</p> <p><strong>Et si 15 minutes de coloriage remplaçaient le scroll du soir ?</strong></p> <h3>✅ Une vraie parenthèse détente</h3> <p>Ce livre de style manga / anime aide à relâcher la pression : on se concentre sur les couleurs, le mental se pose. Idéal le soir ou le week-end.</p> <h3>✅ Des illustrations originales et mignonnes</h3> <p>Des pages au style style manga / anime, pensées pour être agréables à colorier du premier au dernier trait, sans motif trop chargé.</p> <h3>✅ Le cadeau qui fait toujours plaisir</h3> <p>Pour soi ou à offrir : un objet doux, accessible et personnel qui plaît aux ados comme aux adultes.</p> <h3>📦 Caractéristiques</h3> <ul> <li><strong>Type :</strong> Livre de coloriage broché</li> <li><strong>Pages :</strong> ≈ 24-30 pages</li> <li><strong>Papier :</strong> Épais, adapté aux feutres et crayons</li> <li><strong>Format :</strong> Compact, transportable</li> <li><strong>Contenu :</strong> 1 livre de coloriage</li> </ul> <h3>❓ Questions fréquentes</h3> <details><summary>Le papier bave-t-il avec les feutres ?</summary><p>Le papier est épais ; pour les feutres à alcool, glissez une feuille sous la page en cours par précaution.</p></details> <details><summary>Convient-il aux débutants ?</summary><p>Oui, les motifs sont accessibles : aucune technique requise, juste l'envie de colorier.</p></details> <details><summary>Y a-t-il du texte à l'intérieur ?</summary><p>Ce sont des pages à colorier ; le texte est minimal, l'univers est visuel.</p></details> <p><strong>🛒 Offrez-vous cette pause — Livraison offerte dès 39€ d'achat.</strong></p> </div>
A34: coloriage-foot-1 | B34: coloriage foot | C34: [hors thème] Coloriage apaisant art lumineux | D34: https://fr.aliexpress.com/item/1005008906083007.html | E34: 10.39 | F34: 0 | G34: =IF(OR(E34="",F34=""),"",E34+F34) | H34: =IFERROR(VLOOKUP(B34,'Collections'!$C$4:$L$18,10,FALSE),"") | I34: =IFERROR(H34/G34,"") | J34: 5 | K34: 380 | L34: N/D | M34: N/D | N34: N/D | O34: N/D | P34: Aucun angle foot viable (licence) | Q34: HORS THÈME FOOT : aucun coloriage foot générique sans licence (clubs/joueurs protégés) sur AliExpress FR. Coloriage générique listé à titre indicatif ; non vérifié en fiche. | R34: Écarter | S34: 46213 | T34: COLLECTION À REPENSER : 'coloriage foot' non sourçable sans licence. Envisager coloriage sport générique ou retirer la collection. | U34: — (produit écarté, pas de visuels) | W34: — (écarté)
A35: coloriage-foot-2 | B35: coloriage foot | C35: [hors thème] 20 feuilles autocollants 3D enfants | D35: https://fr.aliexpress.com/item/1005010384364245.html | E35: 9.29 | F35: 0 | G35: =IF(OR(E35="",F35=""),"",E35+F35) | H35: =IFERROR(VLOOKUP(B35,'Collections'!$C$4:$L$18,10,FALSE),"") | I35: =IFERROR(H35/G35,"") | J35: 4.9 | K35: 362 | L35: N/D | M35: N/D | N35: N/D | O35: N/D | P35: Aucun angle foot viable (licence) | Q35: HORS THÈME FOOT : aucun coloriage foot générique sans licence (clubs/joueurs protégés) sur AliExpress FR. Coloriage générique listé à titre indicatif ; non vérifié en fiche. | R35: Écarter | S35: 46213 | T35: COLLECTION À REPENSER : 'coloriage foot' non sourçable sans licence. Envisager coloriage sport générique ou retirer la collection. | U35: — (produit écarté, pas de visuels) | W35: — (écarté)
A36: coloriage-foot-3 | B36: coloriage foot | C36: [hors thème] Livre d'objets cachés interactifs | D36: https://fr.aliexpress.com/item/1005010389583636.html | E36: 5.79 | F36: 0 | G36: =IF(OR(E36="",F36=""),"",E36+F36) | H36: =IFERROR(VLOOKUP(B36,'Collections'!$C$4:$L$18,10,FALSE),"") | I36: =IFERROR(H36/G36,"") | J36: 4.6 | K36: 600 | L36: N/D | M36: N/D | N36: N/D | O36: N/D | P36: Aucun angle foot viable (licence) | Q36: HORS THÈME FOOT : aucun coloriage foot générique sans licence (clubs/joueurs protégés) sur AliExpress FR. Coloriage générique listé à titre indicatif ; non vérifié en fiche. | R36: Écarter | S36: 46213 | T36: COLLECTION À REPENSER : 'coloriage foot' non sourçable sans licence. Envisager coloriage sport générique ou retirer la collection. | U36: — (produit écarté, pas de visuels) | W36: — (écarté)
A37: coloriage-foot-4 | B37: coloriage foot | C37: [hors thème] Collection coloriage adultes | D37: https://fr.aliexpress.com/item/1005009103825234.html | E37: 9.99 | F37: 0 | G37: =IF(OR(E37="",F37=""),"",E37+F37) | H37: =IFERROR(VLOOKUP(B37,'Collections'!$C$4:$L$18,10,FALSE),"") | I37: =IFERROR(H37/G37,"") | J37: 4.8 | K37: 199 | L37: N/D | M37: N/D | N37: N/D | O37: N/D | P37: Aucun angle foot viable (licence) | Q37: HORS THÈME FOOT : aucun coloriage foot générique sans licence (clubs/joueurs protégés) sur AliExpress FR. Coloriage générique listé à titre indicatif ; non vérifié en fiche. | R37: Écarter | S37: 46213 | T37: COLLECTION À REPENSER : 'coloriage foot' non sourçable sans licence. Envisager coloriage sport générique ou retirer la collection. | U37: — (produit écarté, pas de visuels) | W37: — (écarté)
A38: coloriage-foot-5 | B38: coloriage foot | C38: [hors thème] Comment dessiner tout : 300 dessins | D38: https://fr.aliexpress.com/item/1005009457392367.html | E38: 12.29 | F38: 0 | G38: =IF(OR(E38="",F38=""),"",E38+F38) | H38: =IFERROR(VLOOKUP(B38,'Collections'!$C$4:$L$18,10,FALSE),"") | I38: =IFERROR(H38/G38,"") | J38: 5 | K38: 108 | L38: N/D | M38: N/D | N38: N/D | O38: N/D | P38: Aucun angle foot viable (licence) | Q38: HORS THÈME FOOT : aucun coloriage foot générique sans licence (clubs/joueurs protégés) sur AliExpress FR. Coloriage générique listé à titre indicatif ; non vérifié en fiche. | R38: Écarter | S38: 46213 | T38: COLLECTION À REPENSER : 'coloriage foot' non sourçable sans licence. Envisager coloriage sport générique ou retirer la collection. | U38: — (produit écarté, pas de visuels) | W38: — (écarté)
A39: coloriage-fille-1 | B39: coloriage fille | C39: Dot-to-dot & chiffres (enfant) | D39: https://fr.aliexpress.com/item/1005009460448734.html | E39: 4.89 | F39: 0 | G39: =IF(OR(E39="",F39=""),"",E39+F39) | H39: =IFERROR(VLOOKUP(B39,'Collections'!$C$4:$L$18,10,FALSE),"") | I39: =IFERROR(H39/G39,"") | J39: 4.9 | K39: 10000 | L39: Choice — vendeur agrégé | M39: 16-20 juil. (~6-10 j) | N39: Choice | O39: Couleur: Num1-20 | P39: Points à relier & chiffres — apprendre en s'amusant | Q39: Papeterie/livre enfant, visuels génériques (OK licence). Vérifier texte intérieur minimal (langue). Thème fille approximatif. | R39: Retenir | S39: 46213 | T39: AliExpress Choice ; livraison gratuite dès 10€ ; note agrégée ; thème 'fille' approximatif (coloriage enfant générique) | U39: PACKSHOT — Hero packshot of the kids activity product «Dot-to-dot & chiffres (enfant)» (magic water / reusable), centered on clean bright pastel background, soft shadow, ultra-sharp, soft pastel kawaii brand aesthetic, cohesive palette (blush pink, cream, mint, lilac), 1:1. LIFESTYLE — A happy child using «Dot-to-dot & chiffres (enfant)» at a bright playful table, colorful, safe, soft daylight, top-down, soft pastel kawaii brand aesthetic, cohesive palette (blush pink, cream, mint, lilac), 1:1. EN SITUATION — Close-up of little hands revealing colors on a cute kids page of «Dot-to-dot & chiffres (enfant)», joyful, shallow depth of field. DÉTAIL — Macro of «Dot-to-dot & chiffres (enfant)» pages and the water pen, cute cute kids illustrations, crisp, colorful. FEATURE — Clean feature image of «Dot-to-dot & chiffres (enfant)» with playful callouts (no mess, reusable, ages 3+), pastel palette, negative space. | V39: .../outputs/coloriage-kawaii-arborescence-2026-07-09/images_produits/39_coloriage-fille_1005009460448734 | W39: Coloriage fille Dot-to-dot & chiffres (enfant) | [Marque] | X39: Dot-to-dot & chiffres (enfant) — coloriage fille | [Marque] | Y39: Dot-to-dot & chiffres (enfant) : pour enfant, sans tache. Livraison rapide, avis vérifiés. Commandez sur [Marque] ! | Z39: <div class="product-desc"> <p>Coloriage fille <strong>« Dot-to-dot &amp; chiffres (enfant) »</strong> — pour enfant, sans tache.</p> <p><strong>Occuper les enfants sans dégât ni écran, c'est possible ?</strong></p> <h3>✅ Zéro tache, 100% amusement</h3> <p>Des pages pensées pour les petites mains, faciles à colorier, sans stress pour les parents.</p> <h3>✅ Développe créativité et concentration</h3> <p>Une activité calme qui occupe les enfants intelligemment, à la maison comme en voyage.</p> <h3>✅ Cadeau malin et abordable</h3> <p>Parfait pour un anniversaire ou une occupation de vacances, à un prix doux.</p> <h3>📦 Caractéristiques</h3> <ul> <li><strong>Type :</strong> Livre / cahier de coloriage enfant</li> <li><strong>Âge conseillé :</strong> Dès 3 ans (petites pièces : sous surveillance)</li> <li><strong>Contenu :</strong> 1 livre de coloriage</li> <li><strong>Illustrations :</strong> Génériques et mignonnes</li> <li><strong>Entretien :</strong> —</li> </ul> <h3>❓ Questions fréquentes</h3> <details><summary>À partir de quel âge ?</summary><p>Conseillé dès 3 ans ; les tout-petits sous la surveillance d'un adulte (petites pièces).</p></details> <details><summary>C'est vraiment réutilisable ?</summary><p>Le livre se colorie une fois ; offrez-en plusieurs pour varier les plaisirs.</p></details> <details><summary>Le produit est-il sûr ?</summary><p>Vérifiez toujours la conformité CE/EN71 ; à utiliser sous surveillance pour les plus jeunes.</p></details> <p><strong>🛒 Faites plaisir à votre enfant — Livraison offerte dès 39€ d'achat.</strong></p> </div>
A40: coloriage-fille-2 | B40: coloriage fille | C40: Peinture aquarelle nomade thème espace (enfant) | D40: https://fr.aliexpress.com/item/1005008144750930.html | E40: 4.79 | F40: 0 | G40: =IF(OR(E40="",F40=""),"",E40+F40) | H40: =IFERROR(VLOOKUP(B40,'Collections'!$C$4:$L$18,10,FALSE),"") | I40: =IFERROR(H40/G40,"") | J40: 4.9 | K40: 5000 | L40: Choice — vendeur agrégé | M40: 16-20 juil. (~6-10 j) | N40: Choice | O40: Couleur: Space | P40: Aquarelle nomade thème espace — sans tache | Q40: Papeterie/livre enfant, visuels génériques (OK licence). Vérifier texte intérieur minimal (langue). Thème fille approximatif. | R40: Retenir | S40: 46213 | T40: AliExpress Choice ; livraison gratuite dès 10€ ; note agrégée ; thème 'fille' approximatif (coloriage enfant générique) | U40: PACKSHOT — Hero packshot of the kids activity product «Peinture aquarelle nomade thème espace (enfant)» (magic water / reusable), centered on clean bright pastel background, soft shadow, ultra-sharp, soft pastel kawaii brand aesthetic, cohesive palette (blush pink, cream, mint, lilac), 1:1. LIFESTYLE — A happy child using «Peinture aquarelle nomade thème espace (enfant)» at a bright playful table, colorful, safe, soft daylight, top-down, soft pastel kawaii brand aesthetic, cohesive palette (blush pink, cream, mint, lilac), 1:1. EN SITUATION — Close-up of little hands revealing colors on a cute kids page of «Peinture aquarelle nomade thème espace (enfant)», joyful, shallow depth of field. DÉTAIL — Macro of «Peinture aquarelle nomade thème espace (enfant)» pages and the water pen, cute cute kids illustrations, crisp, colorful. FEATURE — Clean feature image of «Peinture aquarelle nomade thème espace (enfant)» with playful callouts (no mess, reusable, ages 3+), pastel palette, negative space. | V40: .../outputs/coloriage-kawaii-arborescence-2026-07-09/images_produits/40_coloriage-fille_1005008144750930 | W40: Coloriage fille Peinture aquarelle nomade thème espace ( | [Marque] | X40: Peinture aquarelle nomade thème espace ( — coloriage fille | Y40: Peinture aquarelle nomade thème espace ( : pour enfant, sans tache. Livraison rapide, avis vérifiés. Commandez sur [Marque] ! | Z40: <div class="product-desc"> <p>Coloriage fille <strong>« Peinture aquarelle nomade thème espace ( »</strong> — pour enfant, sans tache.</p> <p><strong>Un cadeau créatif qui plaît vraiment aux enfants ?</strong></p> <h3>✅ Zéro tache, 100% amusement</h3> <p>Des pages pensées pour les petites mains, faciles à colorier, sans stress pour les parents.</p> <h3>✅ Développe créativité et concentration</h3> <p>Une activité calme qui occupe les enfants intelligemment, à la maison comme en voyage.</p> <h3>✅ Cadeau malin et abordable</h3> <p>Parfait pour un anniversaire ou une occupation de vacances, à un prix doux.</p> <h3>📦 Caractéristiques</h3> <ul> <li><strong>Type :</strong> Livre / cahier de coloriage enfant</li> <li><strong>Âge conseillé :</strong> Dès 3 ans (petites pièces : sous surveillance)</li> <li><strong>Contenu :</strong> 1 livre de coloriage</li> <li><strong>Illustrations :</strong> Génériques et mignonnes</li> <li><strong>Entretien :</strong> —</li> </ul> <h3>❓ Questions fréquentes</h3> <details><summary>À partir de quel âge ?</summary><p>Conseillé dès 3 ans ; les tout-petits sous la surveillance d'un adulte (petites pièces).</p></details> <details><summary>C'est vraiment réutilisable ?</summary><p>Le livre se colorie une fois ; offrez-en plusieurs pour varier les plaisirs.</p></details> <details><summary>Le produit est-il sûr ?</summary><p>Vérifiez toujours la conformité CE/EN71 ; à utiliser sous surveillance pour les plus jeunes.</p></details> <p><strong>🛒 Faites plaisir à votre enfant — Livraison offerte dès 39€ d'achat.</strong></p> </div>
A41: coloriage-fille-3 | B41: coloriage fille | C41: Coloriage aquarelle enfant 12 pages | D41: https://fr.aliexpress.com/item/1005006966385910.html | E41: 4.69 | F41: 0 | G41: =IF(OR(E41="",F41=""),"",E41+F41) | H41: =IFERROR(VLOOKUP(B41,'Collections'!$C$4:$L$18,10,FALSE),"") | I41: =IFERROR(H41/G41,"") | J41: 4.8 | K41: 5000 | L41: Choice — vendeur agrégé | M41: 13-25 juil. (~3-15 j) | N41: Choice | O41: Couleur: Diverse Cuisine | P41: Coloriage aquarelle enfant — réutilisable sans tache | Q41: Papeterie/livre enfant, visuels génériques (OK licence). Vérifier texte intérieur minimal (langue). Thème fille approximatif. | R41: Retenir | S41: 46213 | T41: AliExpress Choice ; livraison gratuite dès 10€ ; note agrégée ; thème 'fille' approximatif (coloriage enfant générique) | U41: PACKSHOT — Hero packshot of the kids activity product «Coloriage aquarelle enfant 12 pages» (magic water / reusable), centered on clean bright pastel background, soft shadow, ultra-sharp, soft pastel kawaii brand aesthetic, cohesive palette (blush pink, cream, mint, lilac), 1:1. LIFESTYLE — A happy child using «Coloriage aquarelle enfant 12 pages» at a bright playful table, colorful, safe, soft daylight, top-down, soft pastel kawaii brand aesthetic, cohesive palette (blush pink, cream, mint, lilac), 1:1. EN SITUATION — Close-up of little hands revealing colors on a cute kids page of «Coloriage aquarelle enfant 12 pages», joyful, shallow depth of field. DÉTAIL — Macro of «Coloriage aquarelle enfant 12 pages» pages and the water pen, cute cute kids illustrations, crisp, colorful. FEATURE — Clean feature image of «Coloriage aquarelle enfant 12 pages» with playful callouts (no mess, reusable, ages 3+), pastel palette, negative space. | V41: .../outputs/coloriage-kawaii-arborescence-2026-07-09/images_produits/41_coloriage-fille_1005006966385910 | W41: Coloriage fille aquarelle enfant 12 pages | [Marque] | X41: aquarelle enfant 12 pages — coloriage fille | [Marque] | Y41: aquarelle enfant 12 pages : pour enfant, sans tache. Livraison rapide, avis vérifiés. Commandez sur [Marque] ! | Z41: <div class="product-desc"> <p>Coloriage fille <strong>« aquarelle enfant 12 pages »</strong> — pour enfant, sans tache.</p> <p><strong>Marre des taches de feutre partout ?</strong></p> <h3>✅ Zéro tache, 100% amusement</h3> <p>Des pages pensées pour les petites mains, faciles à colorier, sans stress pour les parents.</p> <h3>✅ Développe créativité et concentration</h3> <p>Une activité calme qui occupe les enfants intelligemment, à la maison comme en voyage.</p> <h3>✅ Cadeau malin et abordable</h3> <p>Parfait pour un anniversaire ou une occupation de vacances, à un prix doux.</p> <h3>📦 Caractéristiques</h3> <ul> <li><strong>Type :</strong> Livre / cahier de coloriage enfant</li> <li><strong>Âge conseillé :</strong> Dès 3 ans (petites pièces : sous surveillance)</li> <li><strong>Contenu :</strong> 1 livre de coloriage</li> <li><strong>Illustrations :</strong> Génériques et mignonnes</li> <li><strong>Entretien :</strong> —</li> </ul> <h3>❓ Questions fréquentes</h3> <details><summary>À partir de quel âge ?</summary><p>Conseillé dès 3 ans ; les tout-petits sous la surveillance d'un adulte (petites pièces).</p></details> <details><summary>C'est vraiment réutilisable ?</summary><p>Le livre se colorie une fois ; offrez-en plusieurs pour varier les plaisirs.</p></details> <details><summary>Le produit est-il sûr ?</summary><p>Vérifiez toujours la conformité CE/EN71 ; à utiliser sous surveillance pour les plus jeunes.</p></details> <p><strong>🛒 Faites plaisir à votre enfant — Livraison offerte dès 39€ d'achat.</strong></p> </div>
A42: coloriage-fille-4 | B42: coloriage fille | C42: Cherche-et-trouve 100+ pages (enfant) | D42: https://fr.aliexpress.com/item/1005010101266777.html | E42: 3.69 | F42: 0 | G42: =IF(OR(E42="",F42=""),"",E42+F42) | H42: =IFERROR(VLOOKUP(B42,'Collections'!$C$4:$L$18,10,FALSE),"") | I42: =IFERROR(H42/G42,"") | J42: 4.7 | K42: 10000 | L42: Choice — vendeur agrégé | M42: 16-20 juil. (~6-10 j) | N42: Choice | O42: Couleur: Look Find | P42: Cherche-et-trouve 100+ pages — occupe les enfants | Q42: Papeterie/livre enfant, visuels génériques (OK licence). Vérifier texte intérieur minimal (langue). Thème fille approximatif. | R42: Retenir | S42: 46213 | T42: AliExpress Choice ; livraison gratuite dès 10€ ; note agrégée ; thème 'fille' approximatif (coloriage enfant générique) | U42: PACKSHOT — Hero packshot of the kids activity product «Cherche-et-trouve 100+ pages (enfant)» (magic water / reusable), centered on clean bright pastel background, soft shadow, ultra-sharp, soft pastel kawaii brand aesthetic, cohesive palette (blush pink, cream, mint, lilac), 1:1. LIFESTYLE — A happy child using «Cherche-et-trouve 100+ pages (enfant)» at a bright playful table, colorful, safe, soft daylight, top-down, soft pastel kawaii brand aesthetic, cohesive palette (blush pink, cream, mint, lilac), 1:1. EN SITUATION — Close-up of little hands revealing colors on a cute kids page of «Cherche-et-trouve 100+ pages (enfant)», joyful, shallow depth of field. DÉTAIL — Macro of «Cherche-et-trouve 100+ pages (enfant)» pages and the water pen, cute cute kids illustrations, crisp, colorful. FEATURE — Clean feature image of «Cherche-et-trouve 100+ pages (enfant)» with playful callouts (no mess, reusable, ages 3+), pastel palette, negative space. | V42: .../outputs/coloriage-kawaii-arborescence-2026-07-09/images_produits/42_coloriage-fille_1005010101266777 | W42: Coloriage fille Cherche-et-trouve 100+ pages (enfant) | [Marque] | X42: Cherche-et-trouve 100+ pages (enfant) — coloriage fille | [ | Y42: Cherche-et-trouve 100+ pages (enfant) : pour enfant, sans tache. Livraison rapide, avis vérifiés. Commandez sur [Marque] ! | Z42: <div class="product-desc"> <p>Coloriage fille <strong>« Cherche-et-trouve 100+ pages (enfant) »</strong> — pour enfant, sans tache.</p> <p><strong>Occuper les enfants sans dégât ni écran, c'est possible ?</strong></p> <h3>✅ Zéro tache, 100% amusement</h3> <p>Des pages pensées pour les petites mains, faciles à colorier, sans stress pour les parents.</p> <h3>✅ Développe créativité et concentration</h3> <p>Une activité calme qui occupe les enfants intelligemment, à la maison comme en voyage.</p> <h3>✅ Cadeau malin et abordable</h3> <p>Parfait pour un anniversaire ou une occupation de vacances, à un prix doux.</p> <h3>📦 Caractéristiques</h3> <ul> <li><strong>Type :</strong> Livre / cahier de coloriage enfant</li> <li><strong>Âge conseillé :</strong> Dès 3 ans (petites pièces : sous surveillance)</li> <li><strong>Contenu :</strong> 1 livre de coloriage</li> <li><strong>Illustrations :</strong> Génériques et mignonnes</li> <li><strong>Entretien :</strong> —</li> </ul> <h3>❓ Questions fréquentes</h3> <details><summary>À partir de quel âge ?</summary><p>Conseillé dès 3 ans ; les tout-petits sous la surveillance d'un adulte (petites pièces).</p></details> <details><summary>C'est vraiment réutilisable ?</summary><p>Le livre se colorie une fois ; offrez-en plusieurs pour varier les plaisirs.</p></details> <details><summary>Le produit est-il sûr ?</summary><p>Vérifiez toujours la conformité CE/EN71 ; à utiliser sous surveillance pour les plus jeunes.</p></details> <p><strong>🛒 Faites plaisir à votre enfant — Livraison offerte dès 39€ d'achat.</strong></p> </div>
A43: coloriage-fille-5 | B43: coloriage fille | C43: Coloriage doodle enfant (cadeau) | D43: https://fr.aliexpress.com/item/1005009709618781.html | E43: 5.09 | F43: 0 | G43: =IF(OR(E43="",F43=""),"",E43+F43) | H43: =IFERROR(VLOOKUP(B43,'Collections'!$C$4:$L$18,10,FALSE),"") | I43: =IFERROR(H43/G43,"") | J43: 4.7 | K43: 4000 | L43: Choice — vendeur agrégé | M43: 13-25 juil. (~3-15 j) | N43: Choice | O43: Couleur: 1 pièce Aléatoire | P43: Coloriage doodle enfant — cadeau anniversaire | Q43: Papeterie/livre enfant, visuels génériques (OK licence). Vérifier texte intérieur minimal (langue). Thème fille approximatif. ATTENTION variante 'Version chinoise' : choisir version sans texte. | R43: Retenir | S43: 46213 | T43: AliExpress Choice ; livraison gratuite dès 10€ ; note agrégée ; thème 'fille' approximatif (coloriage enfant générique) | U43: PACKSHOT — Hero packshot of the kids activity product «Coloriage doodle enfant (cadeau)» (magic water / reusable), centered on clean bright pastel background, soft shadow, ultra-sharp, soft pastel kawaii brand aesthetic, cohesive palette (blush pink, cream, mint, lilac), 1:1. LIFESTYLE — A happy child using «Coloriage doodle enfant (cadeau)» at a bright playful table, colorful, safe, soft daylight, top-down, soft pastel kawaii brand aesthetic, cohesive palette (blush pink, cream, mint, lilac), 1:1. EN SITUATION — Close-up of little hands revealing colors on a cute kids page of «Coloriage doodle enfant (cadeau)», joyful, shallow depth of field. DÉTAIL — Macro of «Coloriage doodle enfant (cadeau)» pages and the water pen, cute cute kids illustrations, crisp, colorful. FEATURE — Clean feature image of «Coloriage doodle enfant (cadeau)» with playful callouts (no mess, reusable, ages 3+), pastel palette, negative space. | V43: .../outputs/coloriage-kawaii-arborescence-2026-07-09/images_produits/43_coloriage-fille_1005009709618781 | W43: Coloriage fille doodle enfant (cadeau) | [Marque] | X43: doodle enfant (cadeau) — coloriage fille | [Marque] | Y43: doodle enfant (cadeau) : pour enfant, sans tache. Livraison rapide, avis vérifiés. Commandez sur [Marque] ! | Z43: <div class="product-desc"> <p>Coloriage fille <strong>« doodle enfant (cadeau) »</strong> — pour enfant, sans tache.</p> <p><strong>Un cadeau créatif qui plaît vraiment aux enfants ?</strong></p> <h3>✅ Zéro tache, 100% amusement</h3> <p>Des pages pensées pour les petites mains, faciles à colorier, sans stress pour les parents.</p> <h3>✅ Développe créativité et concentration</h3> <p>Une activité calme qui occupe les enfants intelligemment, à la maison comme en voyage.</p> <h3>✅ Cadeau malin et abordable</h3> <p>Parfait pour un anniversaire ou une occupation de vacances, à un prix doux.</p> <h3>📦 Caractéristiques</h3> <ul> <li><strong>Type :</strong> Livre / cahier de coloriage enfant</li> <li><strong>Âge conseillé :</strong> Dès 3 ans (petites pièces : sous surveillance)</li> <li><strong>Contenu :</strong> 1 livre de coloriage</li> <li><strong>Illustrations :</strong> Génériques et mignonnes</li> <li><strong>Entretien :</strong> —</li> </ul> <h3>❓ Questions fréquentes</h3> <details><summary>À partir de quel âge ?</summary><p>Conseillé dès 3 ans ; les tout-petits sous la surveillance d'un adulte (petites pièces).</p></details> <details><summary>C'est vraiment réutilisable ?</summary><p>Le livre se colorie une fois ; offrez-en plusieurs pour varier les plaisirs.</p></details> <details><summary>Le produit est-il sûr ?</summary><p>Vérifiez toujours la conformité CE/EN71 ; à utiliser sous surveillance pour les plus jeunes.</p></details> <p><strong>🛒 Faites plaisir à votre enfant — Livraison offerte dès 39€ d'achat.</strong></p> </div>
A44: coloriage-kawaii-fille-1 | B44: coloriage kawaii fille | C44: [ÉCARTÉ licence] Peinture à l'eau Disney/Frozen | D44: https://fr.aliexpress.com/item/1005008248103321.html | E44: 5.19 | F44: 0 | G44: =IF(OR(E44="",F44=""),"",E44+F44) | H44: =IFERROR(VLOOKUP(B44,'Collections'!$C$4:$L$18,10,FALSE),"") | I44: =IFERROR(H44/G44,"") | J44: 4.9 | K44: 5000 | L44: Choice — vendeur agrégé | M44: 18-23 juil. | N44: Choice | O44: Couleur: 4 | P44: Aucun (licence Disney/Frozen) | Q44: ÉCARTÉ : licence Disney/Frozen ('congelée') — visuels protégés. | R44: Écarter | S44: 46213 | T44: AliExpress Choice ; livraison gratuite dès 10€ ; note agrégée ; LICENCE Disney | U44: — (produit écarté, pas de visuels) | W44: — (écarté)
A45: coloriage-kawaii-fille-2 | B45: coloriage kawaii fille | C45: Coloriage château féerique (20 p., fille) | D45: https://fr.aliexpress.com/item/1005010572734415.html | E45: 6.99 | F45: 0 | G45: =IF(OR(E45="",F45=""),"",E45+F45) | H45: =IFERROR(VLOOKUP(B45,'Collections'!$C$4:$L$18,10,FALSE),"") | I45: =IFERROR(H45/G45,"") | J45: 4.9 | K45: 700 | L45: Choice — vendeur agrégé | M45: 16-20 juil. (~6-10 j) | N45: Choice | O45: Couleur: 459 | P45: Coloriage château féerique — cadeau fille, univers magique | Q45: Livre papier, visuels kawaii génériques (OK licence). Vérifier texte intérieur minimal (langue). | R45: Retenir | S45: 46213 | T45: AliExpress Choice ; livraison gratuite dès 10€ ; note agrégée ; marge x2,85 unité (x3+ en lot ≥2) | U45: PACKSHOT — E-commerce hero packshot of the coloring book «Coloriage château féerique (20 p., fille)», cover facing forward, centered on a clean seamless pastel background, soft studio shadow, ultra-sharp, soft pastel kawaii brand aesthetic, cohesive palette (blush pink, cream, mint, lilac), 1:1 square. LIFESTYLE — Top-down flat-lay of «Coloriage château féerique (20 p., fille)» on a cozy pastel desk with colored pencils, a warm drink and a small plush, soft natural morning light, hygge kawaii mood, soft pastel kawaii brand aesthetic, cohesive palette (blush pink, cream, mint, lilac), 1:1. EN SITUATION — Close-up of a person's hands coloring a kawaii girly page from «Coloriage château féerique (20 p., fille)», cozy blanket, shallow depth of field, warm soft tones. DÉTAIL — Macro of the open inner pages of «Coloriage château féerique (20 p., fille)» showing cute kawaii girly line-art illustrations, crisp lines, shallow depth of field. FEATURE — Clean product feature image of «Coloriage château féerique (20 p., fille)» standing upright with minimal text callouts (page count, thick paper, anti-stress), soft pastel kawaii brand aesthetic, cohesive palette (blush pink, cream, mint, lilac), generous negative space for headline. | V45: .../outputs/coloriage-kawaii-arborescence-2026-07-09/images_produits/45_coloriage-kawaii-fille_1005010572734415 | W45: Coloriage kawaii fille château féerique (20 p., fille) | [Marque] | X45: château féerique (20 p., fille) — coloriage kawaii fille | | Y45: château féerique (20 p., fille) : kawaii, girly et mignon. Livraison rapide, avis vérifiés. Commandez sur [Marque] ! | Z45: <div class="product-desc"> <p>Coloriage kawaii fille <strong>« château féerique (20 p., fille) »</strong> — kawaii, girly et mignon.</p> <p><strong>Occuper les enfants sans dégât ni écran, c'est possible ?</strong></p> <h3>✅ Zéro tache, 100% amusement</h3> <p>Des pages pensées pour les petites mains, faciles à colorier, sans stress pour les parents.</p> <h3>✅ Développe créativité et concentration</h3> <p>Une activité calme qui occupe les enfants intelligemment, à la maison comme en voyage.</p> <h3>✅ Cadeau malin et abordable</h3> <p>Parfait pour un anniversaire ou une occupation de vacances, à un prix doux.</p> <h3>📦 Caractéristiques</h3> <ul> <li><strong>Type :</strong> Livre / cahier de coloriage enfant</li> <li><strong>Âge conseillé :</strong> Dès 3 ans (petites pièces : sous surveillance)</li> <li><strong>Contenu :</strong> 1 livre de coloriage</li> <li><strong>Illustrations :</strong> Génériques et mignonnes</li> <li><strong>Entretien :</strong> —</li> </ul> <h3>❓ Questions fréquentes</h3> <details><summary>À partir de quel âge ?</summary><p>Conseillé dès 3 ans ; les tout-petits sous la surveillance d'un adulte (petites pièces).</p></details> <details><summary>C'est vraiment réutilisable ?</summary><p>Le livre se colorie une fois ; offrez-en plusieurs pour varier les plaisirs.</p></details> <details><summary>Le produit est-il sûr ?</summary><p>Vérifiez toujours la conformité CE/EN71 ; à utiliser sous surveillance pour les plus jeunes.</p></details> <p><strong>🛒 Faites plaisir à votre enfant — Livraison offerte dès 39€ d'achat.</strong></p> </div>
A46: coloriage-kawaii-fille-3 | B46: coloriage kawaii fille | C46: Coloriage 'Creepy Kawaii' (papier épais) | D46: https://fr.aliexpress.com/item/1005010089097935.html | E46: 6.09 | F46: 0 | G46: =IF(OR(E46="",F46=""),"",E46+F46) | H46: =IFERROR(VLOOKUP(B46,'Collections'!$C$4:$L$18,10,FALSE),"") | I46: =IFERROR(H46/G46,"") | J46: 4.9 | K46: 700 | L46: Choice — vendeur agrégé | M46: 16-20 juil. (~6-10 j) | N46: Choice | O46: Couleur: G-008 | P46: Coloriage 'creepy kawaii' — mignon-sombre tendance ado | Q46: Livre papier, visuels kawaii génériques (OK licence). Vérifier texte intérieur minimal (langue). | R46: Retenir | S46: 46213 | T46: AliExpress Choice ; livraison gratuite dès 10€ ; note agrégée | U46: PACKSHOT — E-commerce hero packshot of the coloring book «Coloriage 'Creepy Kawaii' (papier épais)», cover facing forward, centered on a clean seamless pastel background, soft studio shadow, ultra-sharp, soft pastel kawaii brand aesthetic, cohesive palette (blush pink, cream, mint, lilac), 1:1 square. LIFESTYLE — Top-down flat-lay of «Coloriage 'Creepy Kawaii' (papier épais)» on a cozy pastel desk with colored pencils, a warm drink and a small plush, soft natural morning light, hygge kawaii mood, soft pastel kawaii brand aesthetic, cohesive palette (blush pink, cream, mint, lilac), 1:1. EN SITUATION — Close-up of a person's hands coloring a kawaii girly page from «Coloriage 'Creepy Kawaii' (papier épais)», cozy blanket, shallow depth of field, warm soft tones. DÉTAIL — Macro of the open inner pages of «Coloriage 'Creepy Kawaii' (papier épais)» showing cute kawaii girly line-art illustrations, crisp lines, shallow depth of field. FEATURE — Clean product feature image of «Coloriage 'Creepy Kawaii' (papier épais)» standing upright with minimal text callouts (page count, thick paper, anti-stress), soft pastel kawaii brand aesthetic, cohesive palette (blush pink, cream, mint, lilac), generous negative space for headline. | V46: .../outputs/coloriage-kawaii-arborescence-2026-07-09/images_produits/46_coloriage-kawaii-fille_1005010089097935 | W46: Coloriage kawaii fille 'Creepy Kawaii' (papier épais) | [Marque] | X46: 'Creepy Kawaii' (papier épais) — coloriage kawaii fille | [ | Y46: 'Creepy Kawaii' (papier épais) : kawaii, girly et mignon. Livraison rapide, avis vérifiés. Commandez sur [Marque] ! | Z46: <div class="product-desc"> <p>Coloriage kawaii fille <strong>« 'Creepy Kawaii' (papier épais) »</strong> — kawaii, girly et mignon.</p> <p><strong>Un cadeau créatif qui plaît vraiment aux enfants ?</strong></p> <h3>✅ Zéro tache, 100% amusement</h3> <p>Des pages pensées pour les petites mains, faciles à colorier, sans stress pour les parents.</p> <h3>✅ Développe créativité et concentration</h3> <p>Une activité calme qui occupe les enfants intelligemment, à la maison comme en voyage.</p> <h3>✅ Cadeau malin et abordable</h3> <p>Parfait pour un anniversaire ou une occupation de vacances, à un prix doux.</p> <h3>📦 Caractéristiques</h3> <ul> <li><strong>Type :</strong> Livre / cahier de coloriage enfant</li> <li><strong>Âge conseillé :</strong> Dès 3 ans (petites pièces : sous surveillance)</li> <li><strong>Contenu :</strong> 1 livre de coloriage</li> <li><strong>Illustrations :</strong> Génériques et mignonnes</li> <li><strong>Entretien :</strong> —</li> </ul> <h3>❓ Questions fréquentes</h3> <details><summary>À partir de quel âge ?</summary><p>Conseillé dès 3 ans ; les tout-petits sous la surveillance d'un adulte (petites pièces).</p></details> <details><summary>C'est vraiment réutilisable ?</summary><p>Le livre se colorie une fois ; offrez-en plusieurs pour varier les plaisirs.</p></details> <details><summary>Le produit est-il sûr ?</summary><p>Vérifiez toujours la conformité CE/EN71 ; à utiliser sous surveillance pour les plus jeunes.</p></details> <p><strong>🛒 Faites plaisir à votre enfant — Livraison offerte dès 39€ d'achat.</strong></p> </div>
A47: coloriage-kawaii-fille-4 | B47: coloriage kawaii fille | C47: Coloriage chats adorables (24 p., relaxation) | D47: https://fr.aliexpress.com/item/1005009278092348.html | E47: 6.59 | F47: 0 | G47: =IF(OR(E47="",F47=""),"",E47+F47) | H47: =IFERROR(VLOOKUP(B47,'Collections'!$C$4:$L$18,10,FALSE),"") | I47: =IFERROR(H47/G47,"") | J47: 4.9 | K47: 700 | L47: Choice — vendeur agrégé | M47: 16-20 juil. (~6-10 j) | N47: Choice | O47: Standard | P47: Coloriage chats adorables — détente girly / cat-lovers | Q47: Livre papier, visuels kawaii génériques (OK licence). Vérifier texte intérieur minimal (langue). | R47: Retenir | S47: 46213 | T47: AliExpress Choice ; livraison gratuite dès 10€ ; note agrégée | U47: PACKSHOT — E-commerce hero packshot of the coloring book «Coloriage chats adorables (24 p., relaxation)», cover facing forward, centered on a clean seamless pastel background, soft studio shadow, ultra-sharp, soft pastel kawaii brand aesthetic, cohesive palette (blush pink, cream, mint, lilac), 1:1 square. LIFESTYLE — Top-down flat-lay of «Coloriage chats adorables (24 p., relaxation)» on a cozy pastel desk with colored pencils, a warm drink and a small plush, soft natural morning light, hygge kawaii mood, soft pastel kawaii brand aesthetic, cohesive palette (blush pink, cream, mint, lilac), 1:1. EN SITUATION — Close-up of a person's hands coloring a kawaii girly page from «Coloriage chats adorables (24 p., relaxation)», cozy blanket, shallow depth of field, warm soft tones. DÉTAIL — Macro of the open inner pages of «Coloriage chats adorables (24 p., relaxation)» showing cute kawaii girly line-art illustrations, crisp lines, shallow depth of field. FEATURE — Clean product feature image of «Coloriage chats adorables (24 p., relaxation)» standing upright with minimal text callouts (page count, thick paper, anti-stress), soft pastel kawaii brand aesthetic, cohesive palette (blush pink, cream, mint, lilac), generous negative space for headline. | V47: .../outputs/coloriage-kawaii-arborescence-2026-07-09/images_produits/47_coloriage-kawaii-fille_1005009278092348 | W47: Coloriage kawaii fille chats adorables (24 p., relaxation) | [Marque] | X47: chats adorables (24 p., relaxation) — coloriage kawaii fill | Y47: chats adorables (24 p., relaxation) : kawaii, girly et mignon. Livraison rapide, avis vérifiés. Commandez sur [Marque] ! | Z47: <div class="product-desc"> <p>Coloriage kawaii fille <strong>« chats adorables (24 p., relaxation) »</strong> — kawaii, girly et mignon.</p> <p><strong>Marre des taches de feutre partout ?</strong></p> <h3>✅ Zéro tache, 100% amusement</h3> <p>Des pages pensées pour les petites mains, faciles à colorier, sans stress pour les parents.</p> <h3>✅ Développe créativité et concentration</h3> <p>Une activité calme qui occupe les enfants intelligemment, à la maison comme en voyage.</p> <h3>✅ Cadeau malin et abordable</h3> <p>Parfait pour un anniversaire ou une occupation de vacances, à un prix doux.</p> <h3>📦 Caractéristiques</h3> <ul> <li><strong>Type :</strong> Livre / cahier de coloriage enfant</li> <li><strong>Âge conseillé :</strong> Dès 3 ans (petites pièces : sous surveillance)</li> <li><strong>Contenu :</strong> 1 livre de coloriage</li> <li><strong>Illustrations :</strong> Génériques et mignonnes</li> <li><strong>Entretien :</strong> —</li> </ul> <h3>❓ Questions fréquentes</h3> <details><summary>À partir de quel âge ?</summary><p>Conseillé dès 3 ans ; les tout-petits sous la surveillance d'un adulte (petites pièces).</p></details> <details><summary>C'est vraiment réutilisable ?</summary><p>Le livre se colorie une fois ; offrez-en plusieurs pour varier les plaisirs.</p></details> <details><summary>Le produit est-il sûr ?</summary><p>Vérifiez toujours la conformité CE/EN71 ; à utiliser sous surveillance pour les plus jeunes.</p></details> <p><strong>🛒 Faites plaisir à votre enfant — Livraison offerte dès 39€ d'achat.</strong></p> </div>
A48: coloriage-kawaii-fille-5 | B48: coloriage kawaii fille | C48: Aquarelle portable fleurs de cerisier (4 f.) | D48: https://fr.aliexpress.com/item/1005007866125727.html | E48: 6.39 | F48: 0 | G48: =IF(OR(E48="",F48=""),"",E48+F48) | H48: =IFERROR(VLOOKUP(B48,'Collections'!$C$4:$L$18,10,FALSE),"") | I48: =IFERROR(H48/G48,"") | J48: 4.7 | K48: 1000 | L48: Choice — vendeur agrégé | M48: 16-20 juil. (~6-10 j) | N48: Choice | O48: Couleur: Cherry blossom | P48: Aquarelle portable fleurs de cerisier — kawaii nomade | Q48: Livre papier, visuels kawaii génériques (OK licence). Vérifier texte intérieur minimal (langue). | R48: Retenir | S48: 46213 | T48: AliExpress Choice ; livraison gratuite dès 10€ ; note agrégée | U48: PACKSHOT — E-commerce hero packshot of the coloring book «Aquarelle portable fleurs de cerisier (4 f.)», cover facing forward, centered on a clean seamless pastel background, soft studio shadow, ultra-sharp, soft pastel kawaii brand aesthetic, cohesive palette (blush pink, cream, mint, lilac), 1:1 square. LIFESTYLE — Top-down flat-lay of «Aquarelle portable fleurs de cerisier (4 f.)» on a cozy pastel desk with colored pencils, a warm drink and a small plush, soft natural morning light, hygge kawaii mood, soft pastel kawaii brand aesthetic, cohesive palette (blush pink, cream, mint, lilac), 1:1. EN SITUATION — Close-up of a person's hands coloring a kawaii girly page from «Aquarelle portable fleurs de cerisier (4 f.)», cozy blanket, shallow depth of field, warm soft tones. DÉTAIL — Macro of the open inner pages of «Aquarelle portable fleurs de cerisier (4 f.)» showing cute kawaii girly line-art illustrations, crisp lines, shallow depth of field. FEATURE — Clean product feature image of «Aquarelle portable fleurs de cerisier (4 f.)» standing upright with minimal text callouts (page count, thick paper, anti-stress), soft pastel kawaii brand aesthetic, cohesive palette (blush pink, cream, mint, lilac), generous negative space for headline. | V48: .../outputs/coloriage-kawaii-arborescence-2026-07-09/images_produits/48_coloriage-kawaii-fille_1005007866125727 | W48: Coloriage kawaii fille Aquarelle portable fleurs de cerisier (4 | [Ma | X48: Aquarelle portable fleurs de cerisier (4 — coloriage kawaii | Y48: Aquarelle portable fleurs de cerisier (4 : kawaii, girly et mignon. Livraison rapide, avis vérifiés. Commandez sur [Marque] ! | Z48: <div class="product-desc"> <p>Coloriage kawaii fille <strong>« Aquarelle portable fleurs de cerisier (4 »</strong> — kawaii, girly et mignon.</p> <p><strong>Occuper les enfants sans dégât ni écran, c'est possible ?</strong></p> <h3>✅ Zéro tache, 100% amusement</h3> <p>Des pages pensées pour les petites mains, faciles à colorier, sans stress pour les parents.</p> <h3>✅ Développe créativité et concentration</h3> <p>Une activité calme qui occupe les enfants intelligemment, à la maison comme en voyage.</p> <h3>✅ Cadeau malin et abordable</h3> <p>Parfait pour un anniversaire ou une occupation de vacances, à un prix doux.</p> <h3>📦 Caractéristiques</h3> <ul> <li><strong>Type :</strong> Livre / cahier de coloriage enfant</li> <li><strong>Âge conseillé :</strong> Dès 3 ans (petites pièces : sous surveillance)</li> <li><strong>Contenu :</strong> 1 livre de coloriage</li> <li><strong>Illustrations :</strong> Génériques et mignonnes</li> <li><strong>Entretien :</strong> —</li> </ul> <h3>❓ Questions fréquentes</h3> <details><summary>À partir de quel âge ?</summary><p>Conseillé dès 3 ans ; les tout-petits sous la surveillance d'un adulte (petites pièces).</p></details> <details><summary>C'est vraiment réutilisable ?</summary><p>Le livre se colorie une fois ; offrez-en plusieurs pour varier les plaisirs.</p></details> <details><summary>Le produit est-il sûr ?</summary><p>Vérifiez toujours la conformité CE/EN71 ; à utiliser sous surveillance pour les plus jeunes.</p></details> <p><strong>🛒 Faites plaisir à votre enfant — Livraison offerte dès 39€ d'achat.</strong></p> </div>
A49: chat-kawaii-1 | B49: chat kawaii | C49: Porte-clés peluche chat noir kawaii | D49: https://fr.aliexpress.com/item/1005010706992197.html | E49: 5.19 | F49: 0 | G49: =IF(OR(E49="",F49=""),"",E49+F49) | H49: =IFERROR(VLOOKUP(B49,'Collections'!$C$4:$L$18,10,FALSE),"") | I49: =IFERROR(H49/G49,"") | J49: 4.9 | K49: 10000 | L49: Choice — vendeur agrégé | M49: 16-22 juil. (~6-12 j) | N49: Choice | O49: Couleur: Chaîne de perles | P49: Porte-clés peluche chat noir — sac / cartable kawaii | Q49: Produit chat kawaii générique, léger (OK licence). Vérifier qualité/finition et cohérence variante. | R49: Retenir | S49: 46213 | T49: AliExpress Choice ; livraison gratuite dès 10€ ; note agrégée | U49: PACKSHOT — Hero packshot of «Porte-clés peluche chat noir kawaii», a cute kawaii cat accessory, centered on clean pastel seamless background, soft shadow, ultra-sharp, soft pastel kawaii brand aesthetic, cohesive palette (blush pink, cream, mint, lilac), 1:1. LIFESTYLE — «Porte-clés peluche chat noir kawaii» styled on a cozy desk / clipped on a pastel bag with kawaii props, soft light, lifestyle, soft pastel kawaii brand aesthetic, cohesive palette (blush pink, cream, mint, lilac), 1:1. EN SITUATION — «Porte-clés peluche chat noir kawaii» in real use (on a bag / a cat interacting with it), cute cozy scene, shallow depth of field. DÉTAIL — Macro of «Porte-clés peluche chat noir kawaii» texture, stitching and details, crisp, soft light. FEATURE — Clean feature image of «Porte-clés peluche chat noir kawaii» with minimal callouts (soft, giftable), soft pastel kawaii brand aesthetic, cohesive palette (blush pink, cream, mint, lilac), negative space. | V49: .../outputs/coloriage-kawaii-arborescence-2026-07-09/images_produits/49_chat-kawaii_1005010706992197 | W49: Chat kawaii Porte-clés peluche chat noir kawaii | [Marque] | X49: Porte-clés peluche chat noir kawaii — chat kawaii | [Marque | Y49: Porte-clés peluche chat noir kawaii : cadeau parfait cat-lover. Livraison rapide, avis vérifiés. Commandez sur [Marque] ! | Z49: <div class="product-desc"> <p>Chat kawaii <strong>« Porte-clés peluche chat noir kawaii »</strong> — cadeau parfait cat-lover.</p> <p><strong>Vous (ou un proche) êtes gaga des chats ?</strong></p> <h3>✅ Le cadeau parfait pour les amoureux des chats</h3> <p>Un accessoire mignon à offrir ou à s'offrir, qui met un sourire à chaque utilisation.</p> <h3>✅ Mignon ET utile</h3> <p>Design kawaii soigné, pensé pour accompagner votre quotidien (sac, bureau, maison).</p> <h3>✅ Qualité soignée</h3> <p>Finitions douces et matières agréables ; un petit objet qui fait son effet.</p> <h3>📦 Caractéristiques</h3> <ul> <li><strong>Thème :</strong> Chat kawaii</li> <li><strong>Matière :</strong> Voir variante (peluche / métal / céramique)</li> <li><strong>Format :</strong> Compact, léger</li> <li><strong>Idéal pour :</strong> Cadeau, décoration, accessoire</li> </ul> <h3>❓ Questions fréquentes</h3> <details><summary>C'est un bon cadeau ?</summary><p>Oui, idéal pour tout amoureux des chats, petit budget et grand effet.</p></details> <details><summary>Les finitions sont-elles correctes ?</summary><p>Nous privilégions des articles bien notés ; vérifiez la variante choisie.</p></details> <details><summary>Livraison en France ?</summary><p>Oui, expédition vers la France (délais indiqués à la commande).</p></details> <p><strong>🛒 Craquez pour ce chat kawaii — Livraison offerte dès 39€ d'achat.</strong></p> </div>
A50: chat-kawaii-2 | B50: chat kawaii | C50: Porte-clés duo chat cœur patchwork | D50: https://fr.aliexpress.com/item/1005010089249102.html | E50: 5.19 | F50: 0 | G50: =IF(OR(E50="",F50=""),"",E50+F50) | H50: =IFERROR(VLOOKUP(B50,'Collections'!$C$4:$L$18,10,FALSE),"") | I50: =IFERROR(H50/G50,"") | J50: 4.9 | K50: 10000 | L50: Choice — vendeur agrégé | M50: 16-20 juil. (~6-10 j) | N50: Choice | O50: Couleur: a pair (paire) | P50: Porte-clés duo chat cœur — cadeau cat-lovers | Q50: Produit chat kawaii générique, léger (OK licence). Vérifier qualité/finition et cohérence variante. | R50: Retenir | S50: 46213 | T50: AliExpress Choice ; livraison gratuite dès 10€ ; note agrégée | U50: PACKSHOT — Hero packshot of «Porte-clés duo chat cœur patchwork», a cute kawaii cat accessory, centered on clean pastel seamless background, soft shadow, ultra-sharp, soft pastel kawaii brand aesthetic, cohesive palette (blush pink, cream, mint, lilac), 1:1. LIFESTYLE — «Porte-clés duo chat cœur patchwork» styled on a cozy desk / clipped on a pastel bag with kawaii props, soft light, lifestyle, soft pastel kawaii brand aesthetic, cohesive palette (blush pink, cream, mint, lilac), 1:1. EN SITUATION — «Porte-clés duo chat cœur patchwork» in real use (on a bag / a cat interacting with it), cute cozy scene, shallow depth of field. DÉTAIL — Macro of «Porte-clés duo chat cœur patchwork» texture, stitching and details, crisp, soft light. FEATURE — Clean feature image of «Porte-clés duo chat cœur patchwork» with minimal callouts (soft, giftable), soft pastel kawaii brand aesthetic, cohesive palette (blush pink, cream, mint, lilac), negative space. | V50: .../outputs/coloriage-kawaii-arborescence-2026-07-09/images_produits/50_chat-kawaii_1005010089249102 | W50: Chat kawaii Porte-clés duo chat cœur patchwork | [Marque] | X50: Porte-clés duo chat cœur patchwork — chat kawaii | [Marque] | Y50: Porte-clés duo chat cœur patchwork : cadeau parfait cat-lover. Livraison rapide, avis vérifiés. Commandez sur [Marque] ! | Z50: <div class="product-desc"> <p>Chat kawaii <strong>« Porte-clés duo chat cœur patchwork »</strong> — cadeau parfait cat-lover.</p> <p><strong>Le petit cadeau qui fait fondre les amoureux des chats ?</strong></p> <h3>✅ Le cadeau parfait pour les amoureux des chats</h3> <p>Un accessoire mignon à offrir ou à s'offrir, qui met un sourire à chaque utilisation.</p> <h3>✅ Mignon ET utile</h3> <p>Design kawaii soigné, pensé pour accompagner votre quotidien (sac, bureau, maison).</p> <h3>✅ Qualité soignée</h3> <p>Finitions douces et matières agréables ; un petit objet qui fait son effet.</p> <h3>📦 Caractéristiques</h3> <ul> <li><strong>Thème :</strong> Chat kawaii</li> <li><strong>Matière :</strong> Voir variante (peluche / métal / céramique)</li> <li><strong>Format :</strong> Compact, léger</li> <li><strong>Idéal pour :</strong> Cadeau, décoration, accessoire</li> </ul> <h3>❓ Questions fréquentes</h3> <details><summary>C'est un bon cadeau ?</summary><p>Oui, idéal pour tout amoureux des chats, petit budget et grand effet.</p></details> <details><summary>Les finitions sont-elles correctes ?</summary><p>Nous privilégions des articles bien notés ; vérifiez la variante choisie.</p></details> <details><summary>Livraison en France ?</summary><p>Oui, expédition vers la France (délais indiqués à la commande).</p></details> <p><strong>🛒 Craquez pour ce chat kawaii — Livraison offerte dès 39€ d'achat.</strong></p> </div>
A51: chat-kawaii-3 | B51: chat kawaii | C51: Porte-clés fidget touches chat (anti-stress) | D51: https://fr.aliexpress.com/item/1005010653366549.html | E51: 7.19 | F51: 0 | G51: =IF(OR(E51="",F51=""),"",E51+F51) | H51: =IFERROR(VLOOKUP(B51,'Collections'!$C$4:$L$18,10,FALSE),"") | I51: =IFERROR(H51/G51,"") | J51: 4.9 | K51: 10000 | L51: Choice — vendeur agrégé | M51: 16-22 juil. (~6-12 j) | N51: Choice | O51: Couleur: 1PC D | P51: Porte-clés fidget touches chat — anti-stress kawaii | Q51: Produit chat kawaii générique, léger (OK licence). Vérifier qualité/finition et cohérence variante. | R51: Retenir | S51: 46213 | T51: AliExpress Choice ; livraison gratuite dès 10€ ; note agrégée | U51: PACKSHOT — Hero packshot of «Porte-clés fidget touches chat (anti-stress)», a cute kawaii cat accessory, centered on clean pastel seamless background, soft shadow, ultra-sharp, soft pastel kawaii brand aesthetic, cohesive palette (blush pink, cream, mint, lilac), 1:1. LIFESTYLE — «Porte-clés fidget touches chat (anti-stress)» styled on a cozy desk / clipped on a pastel bag with kawaii props, soft light, lifestyle, soft pastel kawaii brand aesthetic, cohesive palette (blush pink, cream, mint, lilac), 1:1. EN SITUATION — «Porte-clés fidget touches chat (anti-stress)» in real use (on a bag / a cat interacting with it), cute cozy scene, shallow depth of field. DÉTAIL — Macro of «Porte-clés fidget touches chat (anti-stress)» texture, stitching and details, crisp, soft light. FEATURE — Clean feature image of «Porte-clés fidget touches chat (anti-stress)» with minimal callouts (soft, giftable), soft pastel kawaii brand aesthetic, cohesive palette (blush pink, cream, mint, lilac), negative space. | V51: .../outputs/coloriage-kawaii-arborescence-2026-07-09/images_produits/51_chat-kawaii_1005010653366549 | W51: Chat kawaii Porte-clés fidget touches chat (anti-str | [Marque] | X51: Porte-clés fidget touches chat (anti-str — chat kawaii | [M | Y51: Porte-clés fidget touches chat (anti-str : cadeau parfait cat-lover. Livraison rapide, avis vérifiés. Commandez sur [Marque] ! | Z51: <div class="product-desc"> <p>Chat kawaii <strong>« Porte-clés fidget touches chat (anti-str »</strong> — cadeau parfait cat-lover.</p> <p><strong>Envie d'une touche kawaii au quotidien ?</strong></p> <h3>✅ Le cadeau parfait pour les amoureux des chats</h3> <p>Un accessoire mignon à offrir ou à s'offrir, qui met un sourire à chaque utilisation.</p> <h3>✅ Mignon ET utile</h3> <p>Design kawaii soigné, pensé pour accompagner votre quotidien (sac, bureau, maison).</p> <h3>✅ Qualité soignée</h3> <p>Finitions douces et matières agréables ; un petit objet qui fait son effet.</p> <h3>📦 Caractéristiques</h3> <ul> <li><strong>Thème :</strong> Chat kawaii</li> <li><strong>Matière :</strong> Voir variante (peluche / métal / céramique)</li> <li><strong>Format :</strong> Compact, léger</li> <li><strong>Idéal pour :</strong> Cadeau, décoration, accessoire</li> </ul> <h3>❓ Questions fréquentes</h3> <details><summary>C'est un bon cadeau ?</summary><p>Oui, idéal pour tout amoureux des chats, petit budget et grand effet.</p></details> <details><summary>Les finitions sont-elles correctes ?</summary><p>Nous privilégions des articles bien notés ; vérifiez la variante choisie.</p></details> <details><summary>Livraison en France ?</summary><p>Oui, expédition vers la France (délais indiqués à la commande).</p></details> <p><strong>🛒 Craquez pour ce chat kawaii — Livraison offerte dès 39€ d'achat.</strong></p> </div>
A52: chat-kawaii-4 | B52: chat kawaii | C52: Bol surélevé chat (anti-moustache) | D52: https://fr.aliexpress.com/item/1005008660121856.html | E52: 6.99 | F52: 0 | G52: =IF(OR(E52="",F52=""),"",E52+F52) | H52: =IFERROR(VLOOKUP(B52,'Collections'!$C$4:$L$18,10,FALSE),"") | I52: =IFERROR(H52/G52,"") | J52: 4.9 | K52: 10000 | L52: Choice — vendeur agrégé | M52: 16-20 juil. (~6-10 j) | N52: Choice | O52: Couleur: Black | P52: Bol surélevé ergonomique — confort du chat | Q52: Produit chat kawaii générique, léger (OK licence). Vérifier qualité/finition et cohérence variante. Accessoire animalerie (pas de norme jouet). | R52: Retenir | S52: 46213 | T52: AliExpress Choice ; livraison gratuite dès 10€ ; note agrégée | U52: PACKSHOT — Hero packshot of «Bol surélevé chat (anti-moustache)», a cute kawaii cat accessory, centered on clean pastel seamless background, soft shadow, ultra-sharp, soft pastel kawaii brand aesthetic, cohesive palette (blush pink, cream, mint, lilac), 1:1. LIFESTYLE — «Bol surélevé chat (anti-moustache)» styled on a cozy desk / clipped on a pastel bag with kawaii props, soft light, lifestyle, soft pastel kawaii brand aesthetic, cohesive palette (blush pink, cream, mint, lilac), 1:1. EN SITUATION — «Bol surélevé chat (anti-moustache)» in real use (on a bag / a cat interacting with it), cute cozy scene, shallow depth of field. DÉTAIL — Macro of «Bol surélevé chat (anti-moustache)» texture, stitching and details, crisp, soft light. FEATURE — Clean feature image of «Bol surélevé chat (anti-moustache)» with minimal callouts (soft, giftable), soft pastel kawaii brand aesthetic, cohesive palette (blush pink, cream, mint, lilac), negative space. | V52: .../outputs/coloriage-kawaii-arborescence-2026-07-09/images_produits/52_chat-kawaii_1005008660121856 | W52: Chat kawaii Bol surélevé chat (anti-moustache) | [Marque] | X52: Bol surélevé chat (anti-moustache) — chat kawaii | [Marque] | Y52: Bol surélevé chat (anti-moustache) : cadeau parfait cat-lover. Livraison rapide, avis vérifiés. Commandez sur [Marque] ! | Z52: <div class="product-desc"> <p>Chat kawaii <strong>« Bol surélevé chat (anti-moustache) »</strong> — cadeau parfait cat-lover.</p> <p><strong>Vous (ou un proche) êtes gaga des chats ?</strong></p> <h3>✅ Le cadeau parfait pour les amoureux des chats</h3> <p>Un accessoire mignon à offrir ou à s'offrir, qui met un sourire à chaque utilisation.</p> <h3>✅ Mignon ET utile</h3> <p>Design kawaii soigné, pensé pour accompagner votre quotidien (sac, bureau, maison).</p> <h3>✅ Qualité soignée</h3> <p>Finitions douces et matières agréables ; un petit objet qui fait son effet.</p> <h3>📦 Caractéristiques</h3> <ul> <li><strong>Thème :</strong> Chat kawaii</li> <li><strong>Matière :</strong> Voir variante (peluche / métal / céramique)</li> <li><strong>Format :</strong> Compact, léger</li> <li><strong>Idéal pour :</strong> Cadeau, décoration, accessoire</li> </ul> <h3>❓ Questions fréquentes</h3> <details><summary>C'est un bon cadeau ?</summary><p>Oui, idéal pour tout amoureux des chats, petit budget et grand effet.</p></details> <details><summary>Les finitions sont-elles correctes ?</summary><p>Nous privilégions des articles bien notés ; vérifiez la variante choisie.</p></details> <details><summary>Livraison en France ?</summary><p>Oui, expédition vers la France (délais indiqués à la commande).</p></details> <p><strong>🛒 Craquez pour ce chat kawaii — Livraison offerte dès 39€ d'achat.</strong></p> </div>
A53: chat-kawaii-5 | B53: chat kawaii | C53: Tapis/coussin chat kawaii (flanelle) | D53: https://fr.aliexpress.com/item/1005008248118454.html | E53: 7.49 | F53: 0 | G53: =IF(OR(E53="",F53=""),"",E53+F53) | H53: =IFERROR(VLOOKUP(B53,'Collections'!$C$4:$L$18,10,FALSE),"") | I53: =IFERROR(H53/G53,"") | J53: 4.9 | K53: 10000 | L53: Choice — vendeur agrégé | M53: 16-20 juil. (~6-10 j) | N53: Choice | O53: Couleur: Tête de chat bleu marine | P53: Coussin chat kawaii douillet — hiver | Q53: Produit chat kawaii générique, léger (OK licence). Vérifier qualité/finition et cohérence variante. Accessoire animalerie (pas de norme jouet). | R53: Retenir | S53: 46213 | T53: AliExpress Choice ; livraison gratuite dès 10€ ; note agrégée | U53: PACKSHOT — Hero packshot of «Tapis/coussin chat kawaii (flanelle)», a cute kawaii cat accessory, centered on clean pastel seamless background, soft shadow, ultra-sharp, soft pastel kawaii brand aesthetic, cohesive palette (blush pink, cream, mint, lilac), 1:1. LIFESTYLE — «Tapis/coussin chat kawaii (flanelle)» styled on a cozy desk / clipped on a pastel bag with kawaii props, soft light, lifestyle, soft pastel kawaii brand aesthetic, cohesive palette (blush pink, cream, mint, lilac), 1:1. EN SITUATION — «Tapis/coussin chat kawaii (flanelle)» in real use (on a bag / a cat interacting with it), cute cozy scene, shallow depth of field. DÉTAIL — Macro of «Tapis/coussin chat kawaii (flanelle)» texture, stitching and details, crisp, soft light. FEATURE — Clean feature image of «Tapis/coussin chat kawaii (flanelle)» with minimal callouts (soft, giftable), soft pastel kawaii brand aesthetic, cohesive palette (blush pink, cream, mint, lilac), negative space. | V53: .../outputs/coloriage-kawaii-arborescence-2026-07-09/images_produits/53_chat-kawaii_1005008248118454 | W53: Chat kawaii Tapis/coussin chat kawaii (flanelle) | [Marque] | X53: Tapis/coussin chat kawaii (flanelle) — chat kawaii | [Marqu | Y53: Tapis/coussin chat kawaii (flanelle) : cadeau parfait cat-lover. Livraison rapide, avis vérifiés. Commandez sur [Marque] ! | Z53: <div class="product-desc"> <p>Chat kawaii <strong>« Tapis/coussin chat kawaii (flanelle) »</strong> — cadeau parfait cat-lover.</p> <p><strong>Le petit cadeau qui fait fondre les amoureux des chats ?</strong></p> <h3>✅ Le cadeau parfait pour les amoureux des chats</h3> <p>Un accessoire mignon à offrir ou à s'offrir, qui met un sourire à chaque utilisation.</p> <h3>✅ Mignon ET utile</h3> <p>Design kawaii soigné, pensé pour accompagner votre quotidien (sac, bureau, maison).</p> <h3>✅ Qualité soignée</h3> <p>Finitions douces et matières agréables ; un petit objet qui fait son effet.</p> <h3>📦 Caractéristiques</h3> <ul> <li><strong>Thème :</strong> Chat kawaii</li> <li><strong>Matière :</strong> Voir variante (peluche / métal / céramique)</li> <li><strong>Format :</strong> Compact, léger</li> <li><strong>Idéal pour :</strong> Cadeau, décoration, accessoire</li> </ul> <h3>❓ Questions fréquentes</h3> <details><summary>C'est un bon cadeau ?</summary><p>Oui, idéal pour tout amoureux des chats, petit budget et grand effet.</p></details> <details><summary>Les finitions sont-elles correctes ?</summary><p>Nous privilégions des articles bien notés ; vérifiez la variante choisie.</p></details> <details><summary>Livraison en France ?</summary><p>Oui, expédition vers la France (délais indiqués à la commande).</p></details> <p><strong>🛒 Craquez pour ce chat kawaii — Livraison offerte dès 39€ d'achat.</strong></p> </div>
A54: feutre-acrylique-1 | B54: feutre acrylique | C54: Feutres acryliques 12 couleurs (multi-supports) | D54: https://fr.aliexpress.com/item/1005007805480861.html | E54: 7.09 | F54: 0 | G54: =IF(OR(E54="",F54=""),"",E54+F54) | H54: =IFERROR(VLOOKUP(B54,'Collections'!$C$4:$L$18,10,FALSE),"") | I54: =IFERROR(H54/G54,"") | J54: 4.9 | K54: 10000 | L54: Vendeur AliExpress (non Choice) | M54: 16-20 juil. (~6-10 j) | N54: Non | O54: Couleur: 12 Colors | P54: Feutres acryliques 12 c. — roche/verre/bois | Q54: FEUTRE/MARQUEUR ACRYLIQUE : signaler GPSR + REACH (encre) + étiquetage CLP UE ; exiger FDS + déclaration conformité fournisseur (souvent absents sur AliExpress). Vérifier la variante (nb couleurs) vendue. | R54: Test | S54: 46213 | T54: AliExpress Choice ; livraison gratuite dès 10€ ; prix selon nb de couleurs ; note agrégée ; NON Choice | U54: PACKSHOT — Hero packshot of the art marker set «Feutres acryliques 12 couleurs (multi-supports)», markers neatly fanned out, clean pastel background, studio light, ultra-sharp, soft pastel kawaii brand aesthetic, cohesive palette (blush pink, cream, mint, lilac), 1:1. LIFESTYLE — Top-down flat-lay of «Feutres acryliques 12 couleurs (multi-supports)» beside a colorful hand-drawn artwork on a cozy creative desk, soft light, soft pastel kawaii brand aesthetic, cohesive palette (blush pink, cream, mint, lilac), 1:1. EN SITUATION — Close-up of a hand using «Feutres acryliques 12 couleurs (multi-supports)» to color, vibrant smooth strokes, shallow depth of field. DÉTAIL — Macro of the marker tips and a grid of color swatches on paper, crisp and colorful. FEATURE — Clean feature image of «Feutres acryliques 12 couleurs (multi-supports)» with callouts (number of colors, dual tip, blendable), soft pastel kawaii brand aesthetic, cohesive palette (blush pink, cream, mint, lilac), negative space. | V54: .../outputs/coloriage-kawaii-arborescence-2026-07-09/images_produits/54_feutre-acrylique_1005007805480861 | W54: Feutres acryliques Feutres acryliques 12 couleurs (multi-su | [Marque | X54: Feutres acryliques 12 couleurs (multi-su — feutres acryliqu | Y54: Feutres acryliques 12 couleurs (multi-su : couleurs couvrantes multi-supports. Livraison rapide, avis vérifiés. Commandez sur [Marque] ! | Z54: <div class="product-desc"> <p>Feutres acryliques <strong>« Feutres acryliques 12 couleurs (multi-su »</strong> — couleurs couvrantes multi-supports.</p> <p><strong>Envie de passer au niveau supérieur en dessin ?</strong></p> <h3>✅ Des couleurs riches et couvrantes</h3> <p>Peinture acrylique opaque : couvre tout support (papier, roche, verre, bois, tissu).</p> <h3>✅ Prise en main facile</h3> <p>Pointe agréable et confortable, pour les débutants comme les initiés.</p> <h3>✅ Set complet, prêt à créer</h3> <p>Idéal pour coloriage, lettering, illustration et loisirs créatifs.</p> <h3>📦 Caractéristiques</h3> <ul> <li><strong>Type :</strong> Feutres/marqueurs acryliques</li> <li><strong>Nombre de couleurs :</strong> Selon variante (voir sélection)</li> <li><strong>Supports :</strong> Papier, roche, verre, bois, céramique</li> <li><strong>Contenu :</strong> 1 set de feutres</li> </ul> <h3>❓ Questions fréquentes</h3> <details><summary>Ça traverse le papier ?</summary><p>L'acrylique couvre bien ; sur papier fin, glissez une protection dessous.</p></details> <details><summary>Conformité UE ?</summary><p>Produit d'art : vérifiez l'étiquetage CLP/REACH et la conformité GPSR du fournisseur avant usage.</p></details> <details><summary>Pour débutants ?</summary><p>Oui, aucune expérience requise : on prend le feutre et on colore.</p></details> <p><strong>🛒 Passez à la couleur — Livraison offerte dès 39€ d'achat.</strong></p> </div>
A55: feutre-acrylique-2 | B55: feutre acrylique | C55: Marqueurs brosse acryliques (teintes chair) | D55: https://fr.aliexpress.com/item/1005008854307879.html | E55: 8.79 | F55: 0 | G55: =IF(OR(E55="",F55=""),"",E55+F55) | H55: =IFERROR(VLOOKUP(B55,'Collections'!$C$4:$L$18,10,FALSE),"") | I55: =IFERROR(H55/G55,"") | J55: 4.9 | K55: 10000 | L55: Choice — vendeur agrégé | M55: 16-20 juil. (~6-10 j) | N55: Choice | O55: Couleur: Flesh Tone Series | P55: Marqueurs brosse acryliques — portrait / teintes chair | Q55: FEUTRE/MARQUEUR ACRYLIQUE : signaler GPSR + REACH (encre) + étiquetage CLP UE ; exiger FDS + déclaration conformité fournisseur (souvent absents sur AliExpress). Vérifier la variante (nb couleurs) vendue. | R55: Test | S55: 46213 | T55: AliExpress Choice ; livraison gratuite dès 10€ ; prix selon nb de couleurs ; note agrégée | U55: PACKSHOT — Hero packshot of the art marker set «Marqueurs brosse acryliques (teintes chair)», markers neatly fanned out, clean pastel background, studio light, ultra-sharp, soft pastel kawaii brand aesthetic, cohesive palette (blush pink, cream, mint, lilac), 1:1. LIFESTYLE — Top-down flat-lay of «Marqueurs brosse acryliques (teintes chair)» beside a colorful hand-drawn artwork on a cozy creative desk, soft light, soft pastel kawaii brand aesthetic, cohesive palette (blush pink, cream, mint, lilac), 1:1. EN SITUATION — Close-up of a hand using «Marqueurs brosse acryliques (teintes chair)» to color, vibrant smooth strokes, shallow depth of field. DÉTAIL — Macro of the marker tips and a grid of color swatches on paper, crisp and colorful. FEATURE — Clean feature image of «Marqueurs brosse acryliques (teintes chair)» with callouts (number of colors, dual tip, blendable), soft pastel kawaii brand aesthetic, cohesive palette (blush pink, cream, mint, lilac), negative space. | V55: .../outputs/coloriage-kawaii-arborescence-2026-07-09/images_produits/55_feutre-acrylique_1005008854307879 | W55: Feutres acryliques Marqueurs brosse acryliques (teintes cha | [Marque | X55: Marqueurs brosse acryliques (teintes cha — feutres acryliqu | Y55: Marqueurs brosse acryliques (teintes cha : couleurs couvrantes multi-supports. Livraison rapide, avis vérifiés. Commandez sur [Marque] ! | Z55: <div class="product-desc"> <p>Feutres acryliques <strong>« Marqueurs brosse acryliques (teintes cha »</strong> — couleurs couvrantes multi-supports.</p> <p><strong>Des couleurs qui claquent, sans matériel pro ?</strong></p> <h3>✅ Des couleurs riches et couvrantes</h3> <p>Peinture acrylique opaque : couvre tout support (papier, roche, verre, bois, tissu).</p> <h3>✅ Prise en main facile</h3> <p>Pointe agréable et confortable, pour les débutants comme les initiés.</p> <h3>✅ Set complet, prêt à créer</h3> <p>Idéal pour coloriage, lettering, illustration et loisirs créatifs.</p> <h3>📦 Caractéristiques</h3> <ul> <li><strong>Type :</strong> Feutres/marqueurs acryliques</li> <li><strong>Nombre de couleurs :</strong> Selon variante (voir sélection)</li> <li><strong>Supports :</strong> Papier, roche, verre, bois, céramique</li> <li><strong>Contenu :</strong> 1 set de feutres</li> </ul> <h3>❓ Questions fréquentes</h3> <details><summary>Ça traverse le papier ?</summary><p>L'acrylique couvre bien ; sur papier fin, glissez une protection dessous.</p></details> <details><summary>Conformité UE ?</summary><p>Produit d'art : vérifiez l'étiquetage CLP/REACH et la conformité GPSR du fournisseur avant usage.</p></details> <details><summary>Pour débutants ?</summary><p>Oui, aucune expérience requise : on prend le feutre et on colore.</p></details> <p><strong>🛒 Passez à la couleur — Livraison offerte dès 39€ d'achat.</strong></p> </div>
A56: feutre-acrylique-3 | B56: feutre acrylique | C56: Marqueurs acryliques pointe souple (9 c.) | D56: https://fr.aliexpress.com/item/1005009045288397.html | E56: 9.29 | F56: 0 | G56: =IF(OR(E56="",F56=""),"",E56+F56) | H56: =IFERROR(VLOOKUP(B56,'Collections'!$C$4:$L$18,10,FALSE),"") | I56: =IFERROR(H56/G56,"") | J56: 4.9 | K56: 10000 | L56: Choice — vendeur agrégé | M56: 18-25 juil. (~8-15 j) | N56: Choice | O56: Couleur: Gray Brown Series | P56: Marqueurs acryliques pointe souple — 9 couleurs | Q56: FEUTRE/MARQUEUR ACRYLIQUE : signaler GPSR + REACH (encre) + étiquetage CLP UE ; exiger FDS + déclaration conformité fournisseur (souvent absents sur AliExpress). Vérifier la variante (nb couleurs) vendue. | R56: Test | S56: 46213 | T56: AliExpress Choice ; livraison gratuite dès 10€ ; prix selon nb de couleurs ; note agrégée | U56: PACKSHOT — Hero packshot of the art marker set «Marqueurs acryliques pointe souple (9 c.)», markers neatly fanned out, clean pastel background, studio light, ultra-sharp, soft pastel kawaii brand aesthetic, cohesive palette (blush pink, cream, mint, lilac), 1:1. LIFESTYLE — Top-down flat-lay of «Marqueurs acryliques pointe souple (9 c.)» beside a colorful hand-drawn artwork on a cozy creative desk, soft light, soft pastel kawaii brand aesthetic, cohesive palette (blush pink, cream, mint, lilac), 1:1. EN SITUATION — Close-up of a hand using «Marqueurs acryliques pointe souple (9 c.)» to color, vibrant smooth strokes, shallow depth of field. DÉTAIL — Macro of the marker tips and a grid of color swatches on paper, crisp and colorful. FEATURE — Clean feature image of «Marqueurs acryliques pointe souple (9 c.)» with callouts (number of colors, dual tip, blendable), soft pastel kawaii brand aesthetic, cohesive palette (blush pink, cream, mint, lilac), negative space. | V56: .../outputs/coloriage-kawaii-arborescence-2026-07-09/images_produits/56_feutre-acrylique_1005009045288397 | W56: Feutres acryliques Marqueurs acryliques pointe souple (9 c. | [Marque | X56: Marqueurs acryliques pointe souple (9 c. — feutres acryliqu | Y56: Marqueurs acryliques pointe souple (9 c. : couleurs couvrantes multi-supports. Livraison rapide, avis vérifiés. Commandez sur [Marque] ! | Z56: <div class="product-desc"> <p>Feutres acryliques <strong>« Marqueurs acryliques pointe souple (9 c. »</strong> — couleurs couvrantes multi-supports.</p> <p><strong>Le kit idéal pour créer, débuter ou offrir ?</strong></p> <h3>✅ Des couleurs riches et couvrantes</h3> <p>Peinture acrylique opaque : couvre tout support (papier, roche, verre, bois, tissu).</p> <h3>✅ Prise en main facile</h3> <p>Pointe agréable et confortable, pour les débutants comme les initiés.</p> <h3>✅ Set complet, prêt à créer</h3> <p>Idéal pour coloriage, lettering, illustration et loisirs créatifs.</p> <h3>📦 Caractéristiques</h3> <ul> <li><strong>Type :</strong> Feutres/marqueurs acryliques</li> <li><strong>Nombre de couleurs :</strong> Selon variante (voir sélection)</li> <li><strong>Supports :</strong> Papier, roche, verre, bois, céramique</li> <li><strong>Contenu :</strong> 1 set de feutres</li> </ul> <h3>❓ Questions fréquentes</h3> <details><summary>Ça traverse le papier ?</summary><p>L'acrylique couvre bien ; sur papier fin, glissez une protection dessous.</p></details> <details><summary>Conformité UE ?</summary><p>Produit d'art : vérifiez l'étiquetage CLP/REACH et la conformité GPSR du fournisseur avant usage.</p></details> <details><summary>Pour débutants ?</summary><p>Oui, aucune expérience requise : on prend le feutre et on colore.</p></details> <p><strong>🛒 Passez à la couleur — Livraison offerte dès 39€ d'achat.</strong></p> </div>
... A78: diamond-painting-personnalise-5 | B78: diamond painting personnalisé | C78: Diamond painting résine AB 'fée' photo perso | D78: https://fr.aliexpress.com/item/1005006987632506.html | E78: 5.29 | F78: 0 | G78: =IF(OR(E78="",F78=""),"",E78+F78) | H78: =IFERROR(VLOOKUP(B78,'Collections'!$C$4:$L$18,10,FALSE),"") | I78: =IFERROR(H78/G78,"") | J78: 4.9 | K78: 2000 | L78: Vendeur AliExpress (non Choice) | M78: N/D (custom + expédition Chine) | N78: Non | O78: Couleur: Acrylic Round Drill | P78: Diamond painting résine AB fée — haut de gamme | Q78: PRODUIT PERSONNALISÉ (photo→toile diamant) : VÉRIFIER process d'envoi photo au fournisseur (msg commande), BAT/aperçu avant prod, MOQ, DÉLAI SUPP. (prod custom + Chine, ~2-4 sem). Prix = fonction TAILLE (variante = plus petit format) → grille de prix par format. Fournisseur HOMFUN/RUOPOTY (générique DP). | R78: Retenir | S78: 46213 | T78: Non Choice ; prix = plus petit format (le prix monte avec la taille) ; produit sur-mesure photo ; note agrégée | U78: PACKSHOT — Hero shot of a finished personalized photo diamond painting «Diamond painting résine AB 'fée' photo perso», a sparkling portrait canvas framed, centered on clean pastel background, soft shadow, ultra-sharp, soft pastel kawaii brand aesthetic, cohesive palette (blush pink, cream, mint, lilac), 1:1. KIT — Top-down flat-lay of the diamond painting kit contents for «Diamond painting résine AB 'fée' photo perso»: canvas, colorful resin diamonds in trays, applicator pen and glue, cozy desk, soft pastel kawaii brand aesthetic, cohesive palette (blush pink, cream, mint, lilac), 1:1. EN SITUATION — Close-up of hands placing sparkling diamonds onto the canvas with the applicator pen, warm light, shallow depth of field. DÉTAIL — Macro sparkle detail of the resin diamonds catching the light on the canvas, crisp, bokeh. AVANT/APRÈS — Split concept: a personal photo transformed into a sparkling diamond painting «Diamond painting résine AB 'fée' photo perso», tasteful, minimal callout 'votre photo', soft pastel kawaii brand aesthetic, cohesive palette (blush pink, cream, mint, lilac). | V78: .../outputs/coloriage-kawaii-arborescence-2026-07-09/images_produits/78_diamond-painting-personnalis_1005006987632506 | W78: Diamond painting personnalisé Diamond painting résine AB 'fée' photo | X78: Diamond painting résine AB 'fée' photo p — diamond painting | Y78: Diamond painting résine AB 'fée' photo p : votre photo en tableau scintillant. Livraison rapide, avis vérifiés. Commandez sur [Marque] ! | Z78: <div class="product-desc"> <p>Diamond painting personnalisé <strong>« Diamond painting résine AB 'fée' photo p »</strong> — votre photo en tableau scintillant.</p> <p><strong>Le cadeau 100% personnel et inoubliable ?</strong></p> <h3>✅ Votre photo transformée en tableau de diamants</h3> <p>Envoyez votre photo : nous la transformons en broderie diamant scintillante, unique et pleine d'émotion.</p> <h3>✅ Un loisir créatif relaxant</h3> <p>Placer les diamants, voir l'image prendre vie : une activité apaisante et gratifiante.</p> <h3>✅ Le cadeau qui touche</h3> <p>Anniversaire, couple, souvenir de famille : un présent sur-mesure qui marque.</p> <h3>📦 Caractéristiques</h3> <ul> <li><strong>Type :</strong> Kit diamond painting personnalisé (photo)</li> <li><strong>Taille :</strong> Selon variante (le prix varie avec le format)</li> <li><strong>Contenu :</strong> Toile imprimée + diamants + stylo + accessoires</li> <li><strong>Personnalisation :</strong> À partir de votre photo</li> </ul> <h3>❓ Questions fréquentes</h3> <details><summary>Comment envoyer ma photo ?</summary><p>Après commande, transmettez votre photo (via message/commande) ; un aperçu (BAT) est recommandé avant production.</p></details> <details><summary>Quel délai ?</summary><p>Produit sur-mesure : prévoir un délai de production supplémentaire + expédition (souvent 2 à 4 semaines).</p></details> <details><summary>Quelle taille choisir ?</summary><p>Plus la toile est grande, plus le rendu est détaillé (et le prix monte) : choisissez selon le sujet.</p></details> <p><strong>🛒 Créez votre tableau souvenir — Livraison offerte dès 39€ d'achat.</strong></p> </div>

Sheet Source_Data
A1: Donnees source Ahrefs utilisees
A3: Keyword | B3: Volume | C3: KD | D3: CPC | E3: Informational | F3: Commercial | G3: Transactional | H3: Current position | I3: Current URL | J3: Utilise comme collection
A4: coloriage kawaii | B4: 38000 | C4: 1 | D4: 0.06 | E4: TRUE | F4: TRUE | G4: TRUE | H4: 1 | I4: https://www.amazon.fr/Livre-Coloriage-Kawaii-Festivit%C3%A9s-C%C3%A9l%C3%A9brations/dp/B0CNWWTSY2 | J4: Oui
A5: coloriage adulte | B5: 15000 | C5: 0 | D5: 0.1 | E5: TRUE | F5: TRUE | G5: FALSE | J5: Oui
A6: coloriage magique | B6: 13000 | C6: 3 | D6: 0.08 | E6: TRUE | F6: TRUE | G6: FALSE | H6: 6 | I6: https://www.amazon.fr/coloriage-magique/s?k=coloriage+magique | J6: Oui
A7: coloriage mystere | B7: 12000 | C7: 0 | D7: 0.09 | E7: TRUE | F7: TRUE | G7: TRUE | H7: 3 | I7: https://www.amazon.fr/coloriage-mystere/s?k=coloriage+mystere | J7: Oui
A8: coloriage cosy | B8: 9200 | C8: 0 | D8: 0.11 | E8: TRUE | F8: TRUE | G8: FALSE | H8: 3 | I8: https://www.amazon.fr/livre-coloriage-cosy/s?k=livre+coloriage+cosy | J8: Oui
A9: coloriage manga | B9: 7000 | C9: 0 | D9: 0.07 | E9: TRUE | F9: TRUE | G9: FALSE | H9: 1 | I9: https://www.amazon.fr/Coloriage-Manga-diff%C3%A9rents-adolescents-personnage/dp/B0CMD8PMTV | J9: Oui
A10: coloriage foot | B10: 6600 | C10: 0 | D10: 0.06 | E10: TRUE | F10: TRUE | G10: FALSE | H10: 1 | I10: https://www.amazon.fr/Mon-cahier-coloriages-magiques-Foot/dp/2035992680 | J10: Oui
A11: coloriage fille | B11: 6600 | C11: 0 | E11: TRUE | F11: TRUE | G11: FALSE | H11: 1 | I11: https://www.amazon.fr/Coloriage-Kawaii-Fille-relaxant-anti-stress/dp/B0CVR37GQW | J11: Oui
A12: coloriage kawaii fille | B12: 4800 | C12: 1 | E12: TRUE | F12: TRUE | G12: TRUE | H12: 1 | I12: https://www.amazon.fr/Coloriage-Kawaii-Fille-relaxant-anti-stress/dp/B0CVR37GQW | J12: Oui
A13: chat kawaii | B13: 4200 | C13: 0 | D13: 0.06 | E13: TRUE | F13: TRUE | G13: FALSE | H13: 1 | I13: https://www.amazon.fr/Livre-coloriage-chat-kawaii-japonais/dp/B0CFCX6VP5 | J13: Oui
A14: feutre acrylique | B14: 33000 | C14: 0 | D14: 0.16 | E14: TRUE | F14: TRUE | G14: TRUE | H14: 1 | I14: https://www.amazon.fr/feutre-acrylique/s?k=feutre+acrylique | J14: Oui
A15: feutre a alcool | B15: 5400 | C15: 0 | D15: 0.21 | E15: TRUE | F15: TRUE | G15: TRUE | H15: 5 | I15: https://www.amazon.fr/feutre-a-alcool/s?k=feutre+a+alcool | J15: Oui
A16: trousse kawaii | B16: 3800 | C16: 0 | D16: 0.14 | E16: TRUE | F16: TRUE | G16: TRUE | H16: 1 | I16: https://www.amazon.fr/chiLUER-Trousse-Kawaii-fournitures-adolescentes/dp/B0B9FNCZR6 | J16: Oui
A17: marque page personnalisé | B17: 3700 | C17: 1 | D17: 0.42 | E17: TRUE | F17: TRUE | G17: TRUE | H17: 1 | I17: https://www.amazon.fr/marque-page-personnalisable/s?k=marque+page+personnalisable | J17: Oui
A18: diamond painting personnalisé | B18: 6000 | C18: 2 | D18: 0.71 | E18: TRUE | F18: TRUE | G18: TRUE | H18: 4 | I18: https://www.amazon.fr/Painting-Personnalis%C3%A9-Personnaliser-Diamond-Painting-Personnalisable/dp/B0DF6X2BX5 | J18: Oui

Sheet Notes
A1: Notes et hypotheses
A3: Source CSV | B3: /Users/Hakim/Downloads/amazon.fr-organic-keywords-subdomains-fr-_2026-07-09_19-21-08.csv
A4: Date de travail | B4: 2026-07-10
A5: Regle principale | B5: Chaque page de type Collection reprend un mot-cle exact du CSV ou son accentuation equivalente.
A6: Objectif catalogue | B6: Construire 300+ SKU avec une cible actuelle de 430 SKU.
A7: Positionnement | B7: Boutique mini-marque : kits, carnets, feutres, accessoires et cadeaux physiques.
A8: A eviter | B8: Personnages/licences type Stitch, Disney, manga existant; fichiers gratuits; claims educatifs/sante non prouves.
A9: SEO | B9: Les hubs menu ne doivent pas cannibaliser les collections exact-match.
A10: SEA | B10: Prioriser P1 pour tests Google Shopping/Search, puis P2 selon marge et sourcing.
A11: Critères sourcing | B11: Produit physique léger et non fragile; marge x3 visée; note 4,7+ et 100+ commandes de préférence; livraison France; zéro licence; vendeur et variantes cohérents.
A12: Conformité | B12: Pour les feutres, exiger documentation GPSR/REACH, étiquetage UE et informations matière. Pour les personnalisés, contrôler droits images, BAT et délais.
A13: Veille concurrence | B13: Quatorze acteurs proches qualifiés, dont trois sites français inclus; seuls AICrayons et MyCuttieBox sont vraiment très proches du concept.
A14: Sourcing AliExpress | B14: 75 emplacements sont préparés. Les URL restent vides en attente d'un export AliExpress/DSers ou d'une liste de liens vérifiable.
A15: Mise a jour | B15: Coller un nouvel export Ahrefs et remplacer les volumes/KD/CPC si besoin.

Sheet Pistes_licence_style
A1: PISTES COMPLÉMENTAIRES — hors des 75 lignes validées (feuille Sourcing_AliExpress)
A3: A) COLORIAGES / PRODUITS SOUS LICENCE — INFORMATIF UNIQUEMENT
A4: ⚠️ NE PAS VENDRE SANS AUTORISATION du détenteur de licence (contrefaçon = fermeture Shopify/Stripe, saisie douane, poursuites). Liste destinée à préparer tes demandes de licence. Données niveau recherche (non re-vérifiées en fiche).
A5: Licence / IP | B5: Produit | C5: Prix achat EUR | D5: Note | E5: Ventes | F5: Lien AliExpress | G5: Collection cible | H5: Remarque
A6: Disney / La Reine des Neiges | B6: Livre magique à l'eau Frozen | C6: 5.19 | D6: 4.9 | E6: 5000 | F6: Voir produit | G6: coloriage kawaii fille | H6: Perso Disney protégé
A7: Disney | B7: Jouets dessin peinture à l'eau Disney | C7: 5.09 | D7: 4.7 | E7: 4000 | F7: Voir produit | G7: coloriage fille | H7: Persos Disney
A8: Disney / Reine des Neiges | B8: Puzzle/coloriage Reine des Neiges | C8: 5.79 | D8: 4.7 | E8: 3000 | F8: Voir produit | G8: coloriage fille | H8: Frozen
A9: Disney / Stitch | B9: Crayons de couleur Stitch (12 pcs) | C9: 6.49 | D9: 4.9 | E9: 500 | F9: Voir produit | G9: trousse kawaii | H9: Lilo & Stitch
A10: Pokémon (Nintendo) | B10: Stylos Pokémon Pikachu (5 pcs) | C10: 6.49 | D10: 4.9 | E10: 50000 | F10: Voir produit | G10: trousse / feutre | H10: Pikachu & co
A11: Pokémon (Nintendo) | B11: Figurines/anime Pokémon | C11: 6.19 | D11: 4.8 | E11: 10000 | F11: Voir produit | G11: chat kawaii (déco) | H11: Marque déposée
A12: Sanrio / Hello Kitty | B12: Trousse maquillage Hello Kitty | C12: 5.49 | D12: 4.9 | E12: 10000 | F12: Voir produit | G12: trousse kawaii | H12: Sanrio
A13: DreamWorks / Gabby's Dollhouse | B13: Peluche Gabby's (Mercat) | C13: 7.19 | D13: 4.9 | E13: 10000 | F13: Voir produit | G13: chat kawaii | H13: Gabby's
A14: Paws / Garfield | B14: Peluche Garfield 25cm | C14: 8.69 | D14: 4.9 | E14: 10000 | F14: Voir produit | G14: chat kawaii | H14: Garfield
A15: Studio Ghibli / Totoro | B15: Porte-clés Totoro | C15: 2.76 | D15: 4.8 | E15: 10000 | F15: Voir produit | G15: chat kawaii | H15: Ghibli
A16: Spin Master / Paw Patrol | B16: Livre magique à l'eau Pat'Patrouille | C16: 5.59 | D16: 4.9 | E16: 5000 | F16: Voir produit | G16: coloriage magique | H16: Paw Patrol
A17: A24 / Hazbin Hotel | B17: Marque-page/clip Hazbin | C17: 5.29 | D17: 4.7 | E17: 89 | F17: Voir produit | G17: marque page | H17: Hazbin Hotel
A18: Incredibox / Sprunki | B18: Coloriage Sprunki | C18: 5.69 | D18: 4.8 | E18: 1000 | F18: Voir produit | G18: coloriage manga | H18: Sprunki (jeu)
A20: B) ALTERNATIVES STYLE GÉNÉRIQUE — LÉGALES (ajoutables au catalogue)
A21: Au lieu de (licence) | B21: Produit générique | C21: Prix achat EUR | D21: Note | E21: Ventes | F21: Lien AliExpress | G21: Collection cible | H21: Terme de recherche légal
A22: Disney princesses | B22: Coloriage château féerique (générique) | C22: 6.99 | D22: 4.9 | E22: 700 | F22: Voir produit | G22: coloriage kawaii fille | H22: coloriage princesse / château féerique
A23: Disney / persos filles | B23: Coloriage 'princesse belle fille' générique | C23: 6.79 | D23: 4.9 | E23: 408 | F23: Voir produit | G23: coloriage fille | H23: coloriage princesse generique
A24: Pokémon / monstres | B24: Coloriage 'monstre mignon' générique | C24: 6.29 | D24: 4.7 | E24: 417 | F24: Voir produit | G24: coloriage kawaii fille | H24: coloriage monstre mignon / creepy kawaii
A25: Manga sous licence | B25: Carnet croquis anime débutants (style) | C25: 8.69 | D25: 4.8 | E25: 600 | F25: Voir produit | G25: coloriage manga | H25: apprendre a dessiner anime / how to draw manga
A26: Sanrio / Hello Kitty | B26: Chat kawaii générique (déjà en cat.) | C26: 6.59 | D26: 4.9 | E26: 700 | F26: Voir produit | G26: chat kawaii | H26: coloriage chat kawaii generique
A28: Foot : pas de coloriage foot générique fiable sur AliExpress. Piste légale = créer/commander des visuels foot originaux (POD) OU chercher 'coloriage sport enfant'. Clubs/joueurs = licence obligatoire.

Sheet Prompts_home_collection
A1: PROMPTS IMAGES — HOME & PAGES DE COLLECTION
A2: Marque : coloriages kawaii. Aesthetic : soft pastel kawaii brand aesthetic, cohesive palette (blush pink, cream, mint, lilac).
A4: Zone | B4: Format | C4: Prompt
A5: HOME — Hero desktop | B5: 16:9 | C5: Wide website hero banner for a kawaii coloring brand: a cozy pastel desk flat-lay with a neat stack of cute coloring books, colored pencils, a warm drink and a small plush, soft dreamy morning light, soft pastel kawaii brand aesthetic, cohesive palette (blush pink, cream, mint, lilac), large clean area on the left for a headline, 16:9.
A6: HOME — Hero mobile | B6: 9:16 | C6: Vertical mobile hero for a kawaii coloring brand: top-down cozy desk with a coloring book, pencils and plush, pastel, soft light, soft pastel kawaii brand aesthetic, cohesive palette (blush pink, cream, mint, lilac), clean top area for headline, 9:16.
A7: HOME — Bandeau 'univers' | B7: 21:9 | C7: Ultra-wide lifestyle strip: a person coloring in a cozy blanket nook surrounded by soft pastel decor and plush, warm hygge mood, soft pastel kawaii brand aesthetic, cohesive palette (blush pink, cream, mint, lilac), space for text, 21:9.
A8: HOME — Grille valeurs / icônes | B8: 1:1 | C8: Set of 4 minimalist pastel icons for a kawaii coloring brand (relaxation, thick paper, fast EU shipping, gift-ready), flat clean style, soft pastel kawaii brand aesthetic, cohesive palette (blush pink, cream, mint, lilac), consistent, 1:1 each.
A9: HOME — Bloc 'best-sellers' | B9: 4:5 | C9: Soft pastel product showcase background (empty), gentle gradient and subtle sparkles, soft pastel kawaii brand aesthetic, cohesive palette (blush pink, cream, mint, lilac), for overlaying product cards, 4:5.
A10: BANNIÈRES DE COLLECTION
A11: coloriage kawaii | B11: 16:9 | C11: Collection banner for «coloriage kawaii»: kawaii coloring books & pencils, cozy pastel scene, soft pastel kawaii brand aesthetic, cohesive palette (blush pink, cream, mint, lilac), wide format with clear space for the collection title, 16:9. (No copyrighted characters/logos.)
A12: coloriage adulte | B12: 16:9 | C12: Collection banner for «coloriage adulte»: kawaii coloring books & pencils, cozy pastel scene, soft pastel kawaii brand aesthetic, cohesive palette (blush pink, cream, mint, lilac), wide format with clear space for the collection title, 16:9. (No copyrighted characters/logos.)
A13: coloriage magique | B13: 16:9 | C13: Collection banner for «coloriage magique»: kids magic-water, colorful, cozy pastel scene, soft pastel kawaii brand aesthetic, cohesive palette (blush pink, cream, mint, lilac), wide format with clear space for the collection title, 16:9. (No copyrighted characters/logos.)
A14: coloriage mystere | B14: 16:9 | C14: Collection banner for «coloriage mystere»: kawaii coloring books & pencils, cozy pastel scene, soft pastel kawaii brand aesthetic, cohesive palette (blush pink, cream, mint, lilac), wide format with clear space for the collection title, 16:9. (No copyrighted characters/logos.)
A15: coloriage cosy | B15: 16:9 | C15: Collection banner for «coloriage cosy»: autumnal reading nook, warm drinks, cozy pastel scene, soft pastel kawaii brand aesthetic, cohesive palette (blush pink, cream, mint, lilac), wide format with clear space for the collection title, 16:9. (No copyrighted characters/logos.)
A16: coloriage manga | B16: 16:9 | C16: Collection banner for «coloriage manga»: anime-style desk, screentones, cozy pastel scene, soft pastel kawaii brand aesthetic, cohesive palette (blush pink, cream, mint, lilac), wide format with clear space for the collection title, 16:9. (No copyrighted characters/logos.)
A17: coloriage foot | B17: 16:9 | C17: Collection banner for «coloriage foot»: generic playful football/sport (NO club logo), cozy pastel scene, soft pastel kawaii brand aesthetic, cohesive palette (blush pink, cream, mint, lilac), wide format with clear space for the collection title, 16:9. (No copyrighted characters/logos.)
A18: coloriage fille | B18: 16:9 | C18: Collection banner for «coloriage fille»: kawaii coloring books & pencils, cozy pastel scene, soft pastel kawaii brand aesthetic, cohesive palette (blush pink, cream, mint, lilac), wide format with clear space for the collection title, 16:9. (No copyrighted characters/logos.)
A19: coloriage kawaii fille | B19: 16:9 | C19: Collection banner for «coloriage kawaii fille»: girly pastel, princess/fairy generic, cozy pastel scene, soft pastel kawaii brand aesthetic, cohesive palette (blush pink, cream, mint, lilac), wide format with clear space for the collection title, 16:9. (No copyrighted characters/logos.)
A20: chat kawaii | B20: 16:9 | C20: Collection banner for «chat kawaii»: cute cats and plush, cozy pastel scene, soft pastel kawaii brand aesthetic, cohesive palette (blush pink, cream, mint, lilac), wide format with clear space for the collection title, 16:9. (No copyrighted characters/logos.)
A21: feutre acrylique | B21: 16:9 | C21: Collection banner for «feutre acrylique»: colorful markers & swatches, cozy pastel scene, soft pastel kawaii brand aesthetic, cohesive palette (blush pink, cream, mint, lilac), wide format with clear space for the collection title, 16:9. (No copyrighted characters/logos.)
A22: feutre a alcool | B22: 16:9 | C22: Collection banner for «feutre a alcool»: markers & sketch art, cozy pastel scene, soft pastel kawaii brand aesthetic, cohesive palette (blush pink, cream, mint, lilac), wide format with clear space for the collection title, 16:9. (No copyrighted characters/logos.)
... A25: diamond painting personnalisé | B25: 16:9 | C25: Collection banner for «diamond painting personnalisé»: sparkling diamonds & canvas, cozy pastel scene, soft pastel kawaii brand aesthetic, cohesive palette (blush pink, cream, mint, lilac), wide format with clear space for the collection title, 16:9. (No copyrighted characters/logos.)
